Workbook

Sheet README
A1: Extraction review – R1 vs R2 (pilot, 5 studies)
A2: Inputs: R1 = r1_retrieval_1.ods (venue_type re-reviewed via Scimago) · R2 = r2_extraction_v4.ods (schema 0.9.0). Identical structure; meta sheets differ only in boolean encoding (no content differences).
A4: Sheets
A5: Summary – open/resolved counts per study and field group; per-field raw agreement (live formulas).
A6: Comparison – one row per value field where R1 ≠ R2; the Field column carries the schema annotation (type, definition, allowed values) from the extraction-file header notes. Resolve here: fill the yellow columns.
A7: Metrics_Comparison – reported_metrics aligned by best match (name+value similarity); decide which entries to keep.
A8: Reasoning_Only – reasoning/rationale texts that differ although the value agrees (or is listed in Comparison). Reference only; no decision required.
A9: Review_Version – consensus record in the original wide layout. Agreed values are final (green); disagreements pull the consensus from Comparison automatically and show ⚠ UNRESOLVED until Status = Resolved (red).
A10: R1_studies / R2_studies / R1_metrics / R2_metrics – unmodified source data.
A12: Normalisation before comparing
A13: Booleans TRUE/1 and FALSE/0 treated as equal; multi-select fields compared as sets (order ignored); whitespace collapsed. Case-only differences listed as Low.
A15: Priority
... A27: Blue = re-coded under schema v0.10.0 (repeated_runs free text; efficiency_metrics_reported yes/partially/no; data_available full/partial/none).

Sheet Summary
A1: Disagreements per study
A2: Study | B2: High | C2: Medium | D2: Low | E2: Total | F2: Resolved | G2: Escalated R3 | H2: Open | I2: % resolved | J2: Metrics: identical | K2: Metrics: differs | L2: Metrics: only R1 | M2: Metrics: only R2
A3: S1 – Schmitt et al. (2026) | B3: =COUNTIFS(Comparison!$B$2:$B$164,$A3,Comparison!$F$2:$F$164,"High") -> 13 | C3: =COUNTIFS(Comparison!$B$2:$B$164,$A3,Comparison!$F$2:$F$164,"Medium") -> 11 | D3: =COUNTIFS(Comparison!$B$2:$B$164,$A3,Comparison!$F$2:$F$164,"Low") -> 1 | E3: =SUM(B3:D3) -> 25 | F3: =COUNTIFS(Comparison!$B$2:$B$164,$A3,Comparison!$N$2:$N$164,"Resolved") -> 25 | G3: =COUNTIFS(Comparison!$B$2:$B$164,$A3,Comparison!$N$2:$N$164,"Escalate-R3") -> 0 | H3: =E3-F3 -> 0 | I3: =IF(E3=0,1,F3/E3) -> 1 | J3: =COUNTIFS(Metrics_Comparison!$A$2:$A$80,$A3,Metrics_Comparison!$B$2:$B$80,"Identical") -> 0 | K3: =COUNTIFS(Metrics_Comparison!$A$2:$A$80,$A3,Metrics_Comparison!$B$2:$B$80,"Matched – differs") -> 4 | L3: =COUNTIFS(Metrics_Comparison!$A$2:$A$80,$A3,Metrics_Comparison!$B$2:$B$80,"Only R1") -> 11 | M3: =COUNTIFS(Metrics_Comparison!$A$2:$A$80,$A3,Metrics_Comparison!$B$2:$B$80,"Only R2") -> 8
A4: S2 – Werheid et al. (2025) | B4: =COUNTIFS(Comparison!$B$2:$B$164,$A4,Comparison!$F$2:$F$164,"High") -> 14 | C4: =COUNTIFS(Comparison!$B$2:$B$164,$A4,Comparison!$F$2:$F$164,"Medium") -> 17 | D4: =COUNTIFS(Comparison!$B$2:$B$164,$A4,Comparison!$F$2:$F$164,"Low") -> 0 | E4: =SUM(B4:D4) -> 31 | F4: =COUNTIFS(Comparison!$B$2:$B$164,$A4,Comparison!$N$2:$N$164,"Resolved") -> 31 | G4: =COUNTIFS(Comparison!$B$2:$B$164,$A4,Comparison!$N$2:$N$164,"Escalate-R3") -> 0 | H4: =E4-F4 -> 0 | I4: =IF(E4=0,1,F4/E4) -> 1 | J4: =COUNTIFS(Metrics_Comparison!$A$2:$A$80,$A4,Metrics_Comparison!$B$2:$B$80,"Identical") -> 0 | K4: =COUNTIFS(Metrics_Comparison!$A$2:$A$80,$A4,Metrics_Comparison!$B$2:$B$80,"Matched – differs") -> 4 | L4: =COUNTIFS(Metrics_Comparison!$A$2:$A$80,$A4,Metrics_Comparison!$B$2:$B$80,"Only R1") -> 0 | M4: =COUNTIFS(Metrics_Comparison!$A$2:$A$80,$A4,Metrics_Comparison!$B$2:$B$80,"Only R2") -> 0
A5: S3 – Hu et al. (2026) | B5: =COUNTIFS(Comparison!$B$2:$B$164,$A5,Comparison!$F$2:$F$164,"High") -> 22 | C5: =COUNTIFS(Comparison!$B$2:$B$164,$A5,Comparison!$F$2:$F$164,"Medium") -> 17 | D5: =COUNTIFS(Comparison!$B$2:$B$164,$A5,Comparison!$F$2:$F$164,"Low") -> 1 | E5: =SUM(B5:D5) -> 40 | F5: =COUNTIFS(Comparison!$B$2:$B$164,$A5,Comparison!$N$2:$N$164,"Resolved") -> 40 | G5: =COUNTIFS(Comparison!$B$2:$B$164,$A5,Comparison!$N$2:$N$164,"Escalate-R3") -> 0 | H5: =E5-F5 -> 0 | I5: =IF(E5=0,1,F5/E5) -> 1 | J5: =COUNTIFS(Metrics_Comparison!$A$2:$A$80,$A5,Metrics_Comparison!$B$2:$B$80,"Identical") -> 0 | K5: =COUNTIFS(Metrics_Comparison!$A$2:$A$80,$A5,Metrics_Comparison!$B$2:$B$80,"Matched – differs") -> 5 | L5: =COUNTIFS(Metrics_Comparison!$A$2:$A$80,$A5,Metrics_Comparison!$B$2:$B$80,"Only R1") -> 10 | M5: =COUNTIFS(Metrics_Comparison!$A$2:$A$80,$A5,Metrics_Comparison!$B$2:$B$80,"Only R2") -> 4
A6: S4 – Gao et al. (2026) | B6: =COUNTIFS(Comparison!$B$2:$B$164,$A6,Comparison!$F$2:$F$164,"High") -> 17 | C6: =COUNTIFS(Comparison!$B$2:$B$164,$A6,Comparison!$F$2:$F$164,"Medium") -> 17 | D6: =COUNTIFS(Comparison!$B$2:$B$164,$A6,Comparison!$F$2:$F$164,"Low") -> 0 | E6: =SUM(B6:D6) -> 34 | F6: =COUNTIFS(Comparison!$B$2:$B$164,$A6,Comparison!$N$2:$N$164,"Resolved") -> 34 | G6: =COUNTIFS(Comparison!$B$2:$B$164,$A6,Comparison!$N$2:$N$164,"Escalate-R3") -> 0 | H6: =E6-F6 -> 0 | I6: =IF(E6=0,1,F6/E6) -> 1 | J6: =COUNTIFS(Metrics_Comparison!$A$2:$A$80,$A6,Metrics_Comparison!$B$2:$B$80,"Identical") -> 0 | K6: =COUNTIFS(Metrics_Comparison!$A$2:$A$80,$A6,Metrics_Comparison!$B$2:$B$80,"Matched – differs") -> 13 | L6: =COUNTIFS(Metrics_Comparison!$A$2:$A$80,$A6,Metrics_Comparison!$B$2:$B$80,"Only R1") -> 16 | M6: =COUNTIFS(Metrics_Comparison!$A$2:$A$80,$A6,Metrics_Comparison!$B$2:$B$80,"Only R2") -> 0
A7: S5 – Simchi-Levi et al. (2025) | B7: =COUNTIFS(Comparison!$B$2:$B$164,$A7,Comparison!$F$2:$F$164,"High") -> 16 | C7: =COUNTIFS(Comparison!$B$2:$B$164,$A7,Comparison!$F$2:$F$164,"Medium") -> 17 | D7: =COUNTIFS(Comparison!$B$2:$B$164,$A7,Comparison!$F$2:$F$164,"Low") -> 0 | E7: =SUM(B7:D7) -> 33 | F7: =COUNTIFS(Comparison!$B$2:$B$164,$A7,Comparison!$N$2:$N$164,"Resolved") -> 33 | G7: =COUNTIFS(Comparison!$B$2:$B$164,$A7,Comparison!$N$2:$N$164,"Escalate-R3") -> 0 | H7: =E7-F7 -> 0 | I7: =IF(E7=0,1,F7/E7) -> 1 | J7: =COUNTIFS(Metrics_Comparison!$A$2:$A$80,$A7,Metrics_Comparison!$B$2:$B$80,"Identical") -> 0 | K7: =COUNTIFS(Metrics_Comparison!$A$2:$A$80,$A7,Metrics_Comparison!$B$2:$B$80,"Matched – differs") -> 3 | L7: =COUNTIFS(Metrics_Comparison!$A$2:$A$80,$A7,Metrics_Comparison!$B$2:$B$80,"Only R1") -> 1 | M7: =COUNTIFS(Metrics_Comparison!$A$2:$A$80,$A7,Metrics_Comparison!$B$2:$B$80,"Only R2") -> 0
A8: Total | B8: =SUM(B3:B7) -> 82 | C8: =SUM(C3:C7) -> 79 | D8: =SUM(D3:D7) -> 2 | E8: =SUM(E3:E7) -> 163 | F8: =SUM(F3:F7) -> 163 | G8: =SUM(G3:G7) -> 0 | H8: =SUM(H3:H7) -> 0 | I8: =IF(E8=0,1,F8/E8) -> 1 | J8: =SUM(J3:J7) -> 0 | K8: =SUM(K3:K7) -> 29 | L8: =SUM(L3:L7) -> 38 | M8: =SUM(M3:M7) -> 12
A10: Disagreements per field group
A11: Field group | B11: High | C11: Medium | D11: Low | E11: Total | F11: Resolved | G11: Open
A12: study | B12: =COUNTIFS(Comparison!$C$2:$C$164,$A12,Comparison!$F$2:$F$164,"High") -> 0 | C12: =COUNTIFS(Comparison!$C$2:$C$164,$A12,Comparison!$F$2:$F$164,"Medium") -> 1 | D12: =COUNTIFS(Comparison!$C$2:$C$164,$A12,Comparison!$F$2:$F$164,"Low") -> 0 | E12: =SUM(B12:D12) -> 1 | F12: =COUNTIFS(Comparison!$C$2:$C$164,$A12,Comparison!$N$2:$N$164,"Resolved") -> 1 | G12: =E12-F12 -> 0
A13: bibliographic_metadata | B13: =COUNTIFS(Comparison!$C$2:$C$164,$A13,Comparison!$F$2:$F$164,"High") -> 0 | C13: =COUNTIFS(Comparison!$C$2:$C$164,$A13,Comparison!$F$2:$F$164,"Medium") -> 7 | D13: =COUNTIFS(Comparison!$C$2:$C$164,$A13,Comparison!$F$2:$F$164,"Low") -> 0 | E13: =SUM(B13:D13) -> 7 | F13: =COUNTIFS(Comparison!$C$2:$C$164,$A13,Comparison!$N$2:$N$164,"Resolved") -> 7 | G13: =E13-F13 -> 0
A14: study_characterization | B14: =COUNTIFS(Comparison!$C$2:$C$164,$A14,Comparison!$F$2:$F$164,"High") -> 1 | C14: =COUNTIFS(Comparison!$C$2:$C$164,$A14,Comparison!$F$2:$F$164,"Medium") -> 9 | D14: =COUNTIFS(Comparison!$C$2:$C$164,$A14,Comparison!$F$2:$F$164,"Low") -> 2 | E14: =SUM(B14:D14) -> 12 | F14: =COUNTIFS(Comparison!$C$2:$C$164,$A14,Comparison!$N$2:$N$164,"Resolved") -> 12 | G14: =E14-F14 -> 0
A15: strategic_planning_scope | B15: =COUNTIFS(Comparison!$C$2:$C$164,$A15,Comparison!$F$2:$F$164,"High") -> 16 | C15: =COUNTIFS(Comparison!$C$2:$C$164,$A15,Comparison!$F$2:$F$164,"Medium") -> 8 | D15: =COUNTIFS(Comparison!$C$2:$C$164,$A15,Comparison!$F$2:$F$164,"Low") -> 0 | E15: =SUM(B15:D15) -> 24 | F15: =COUNTIFS(Comparison!$C$2:$C$164,$A15,Comparison!$N$2:$N$164,"Resolved") -> 24 | G15: =E15-F15 -> 0
A16: llm_intervention | B16: =COUNTIFS(Comparison!$C$2:$C$164,$A16,Comparison!$F$2:$F$164,"High") -> 17 | C16: =COUNTIFS(Comparison!$C$2:$C$164,$A16,Comparison!$F$2:$F$164,"Medium") -> 16 | D16: =COUNTIFS(Comparison!$C$2:$C$164,$A16,Comparison!$F$2:$F$164,"Low") -> 0 | E16: =SUM(B16:D16) -> 33 | F16: =COUNTIFS(Comparison!$C$2:$C$164,$A16,Comparison!$N$2:$N$164,"Resolved") -> 33 | G16: =E16-F16 -> 0
A17: or_substrate | B17: =COUNTIFS(Comparison!$C$2:$C$164,$A17,Comparison!$F$2:$F$164,"High") -> 9 | C17: =COUNTIFS(Comparison!$C$2:$C$164,$A17,Comparison!$F$2:$F$164,"Medium") -> 4 | D17: =COUNTIFS(Comparison!$C$2:$C$164,$A17,Comparison!$F$2:$F$164,"Low") -> 0 | E17: =SUM(B17:D17) -> 13 | F17: =COUNTIFS(Comparison!$C$2:$C$164,$A17,Comparison!$N$2:$N$164,"Resolved") -> 13 | G17: =E17-F17 -> 0
A18: evaluation_and_outcomes | B18: =COUNTIFS(Comparison!$C$2:$C$164,$A18,Comparison!$F$2:$F$164,"High") -> 8 | C18: =COUNTIFS(Comparison!$C$2:$C$164,$A18,Comparison!$F$2:$F$164,"Medium") -> 19 | D18: =COUNTIFS(Comparison!$C$2:$C$164,$A18,Comparison!$F$2:$F$164,"Low") -> 0 | E18: =SUM(B18:D18) -> 27 | F18: =COUNTIFS(Comparison!$C$2:$C$164,$A18,Comparison!$N$2:$N$164,"Resolved") -> 27 | G18: =E18-F18 -> 0
A19: record | B19: =COUNTIFS(Comparison!$C$2:$C$164,$A19,Comparison!$F$2:$F$164,"High") -> 4 | C19: =COUNTIFS(Comparison!$C$2:$C$164,$A19,Comparison!$F$2:$F$164,"Medium") -> 0 | D19: =COUNTIFS(Comparison!$C$2:$C$164,$A19,Comparison!$F$2:$F$164,"Low") -> 0 | E19: =SUM(B19:D19) -> 4 | F19: =COUNTIFS(Comparison!$C$2:$C$164,$A19,Comparison!$N$2:$N$164,"Resolved") -> 4 | G19: =E19-F19 -> 0
A20: retrieval_traceability | B20: =COUNTIFS(Comparison!$C$2:$C$164,$A20,Comparison!$F$2:$F$164,"High") -> 0 | C20: =COUNTIFS(Comparison!$C$2:$C$164,$A20,Comparison!$F$2:$F$164,"Medium") -> 0 | D20: =COUNTIFS(Comparison!$C$2:$C$164,$A20,Comparison!$F$2:$F$164,"Low") -> 0 | E20: =SUM(B20:D20) -> 0 | F20: =COUNTIFS(Comparison!$C$2:$C$164,$A20,Comparison!$N$2:$N$164,"Resolved") -> 0 | G20: =E20-F20 -> 0
A21: gap_indicators | B21: =COUNTIFS(Comparison!$C$2:$C$164,$A21,Comparison!$F$2:$F$164,"High") -> 15 | C21: =COUNTIFS(Comparison!$C$2:$C$164,$A21,Comparison!$F$2:$F$164,"Medium") -> 15 | D21: =COUNTIFS(Comparison!$C$2:$C$164,$A21,Comparison!$F$2:$F$164,"Low") -> 0 | E21: =SUM(B21:D21) -> 30 | F21: =COUNTIFS(Comparison!$C$2:$C$164,$A21,Comparison!$N$2:$N$164,"Resolved") -> 30 | G21: =E21-F21 -> 0
A22: quality_appraisal | B22: =COUNTIFS(Comparison!$C$2:$C$164,$A22,Comparison!$F$2:$F$164,"High") -> 12 | C22: =COUNTIFS(Comparison!$C$2:$C$164,$A22,Comparison!$F$2:$F$164,"Medium") -> 0 | D22: =COUNTIFS(Comparison!$C$2:$C$164,$A22,Comparison!$F$2:$F$164,"Low") -> 0 | E22: =SUM(B22:D22) -> 12 | F22: =COUNTIFS(Comparison!$C$2:$C$164,$A22,Comparison!$N$2:$N$164,"Resolved") -> 12 | G22: =E22-F22 -> 0
A24: Raw agreement per field (n = 5 studies; value fields only)
A25: Field | B25: Type | C25: Studies disagreeing | D25: Raw agreement
A26: schema_version | B26: categorical | C26: =COUNTIFS(Comparison!$D$2:$D$164,$A26) -> 0 | D26: =1-C26/5 -> 1
A27: study_id | B27: categorical | C27: =COUNTIFS(Comparison!$D$2:$D$164,$A27) -> 0 | D27: =1-C27/5 -> 1
A28: bibliographic_metadata.doi | B28: free-text | C28: =COUNTIFS(Comparison!$D$2:$D$164,$A28) -> 0 | D28: =1-C28/5 -> 1
A29: bibliographic_metadata.title | B29: free-text | C29: =COUNTIFS(Comparison!$D$2:$D$164,$A29) -> 0 | D29: =1-C29/5 -> 1
A30: bibliographic_metadata.authors | B30: free-text | C30: =COUNTIFS(Comparison!$D$2:$D$164,$A30) -> 0 | D30: =1-C30/5 -> 1
A31: bibliographic_metadata.affiliations | B31: free-text | C31: =COUNTIFS(Comparison!$D$2:$D$164,$A31) -> 0 | D31: =1-C31/5 -> 1
A32: bibliographic_metadata.country | B32: free-text | C32: =COUNTIFS(Comparison!$D$2:$D$164,$A32) -> 0 | D32: =1-C32/5 -> 1
A33: bibliographic_metadata.year | B33: categorical | C33: =COUNTIFS(Comparison!$D$2:$D$164,$A33) -> 0 | D33: =1-C33/5 -> 1
A34: bibliographic_metadata.venue | B34: free-text | C34: =COUNTIFS(Comparison!$D$2:$D$164,$A34) -> 0 | D34: =1-C34/5 -> 1
A35: bibliographic_metadata.venue_type | B35: categorical | C35: =COUNTIFS(Comparison!$D$2:$D$164,$A35) -> 0 | D35: =1-C35/5 -> 1
A36: bibliographic_metadata.language | B36: categorical | C36: =COUNTIFS(Comparison!$D$2:$D$164,$A36) -> 0 | D36: =1-C36/5 -> 1
A37: bibliographic_metadata.funding_source | B37: free-text | C37: =COUNTIFS(Comparison!$D$2:$D$164,$A37) -> 0 | D37: =1-C37/5 -> 1
... A132: study_type_category | B132: categorical | C132: =COUNTIFS(Comparison!$D$2:$D$164,$A132) -> 0 | D132: =1-C132/5 -> 1

Sheet Comparison
A1: ID | B1: Study | C1: Field group | D1: Field | E1: Type | F1: Priority | G1: Difference | H1: R1 value | I1: R2 value | J1: R1 reasoning | K1: R2 reasoning | L1: Consensus value | M1: Consensus reasoning | N1: Status | O1: Resolution note | P1: Decided by | Q1: Triage (post-High) | R1: Triage rationale
A2: D001 | B2: S1 – Schmitt et al. (2026) | C2: study_characterization | D2: study_characterization.research_type Type: ResearchType Research type of the paper's contribution (Wieringa et al. 2006 facet). Lab/benchmark evaluation -> validation-research; evaluation in operational practice -> evaluation-research. Types: - validation-research: Novel technique evaluated in the lab / artificial setting (experiments, simulations, benchmarks, prototype on test cases), not yet used in practice - evaluation-research: Technique evaluated in practice (naturalistic setting: real organisation, real users, real data in operational use), incl. industrial case studies - solution-proposal: Novel or significantly extended technique, argued for with a small example or none; no thorough evaluation - philosophical-paper: New way of looking at the field: taxonomy, conceptual framework, research agenda - opinion-paper: Personal opinion on what is good or bad, not grounded in related work or method - experience-paper: Practitioner's account of what was done in practice and how it went | E2: categorical | F2: High | G2: Only R1: validation-research | Only R2: evaluation-research | H2: validation-research | I2: evaluation-research | J2: The paper proposes a novel end-to-end LLM-driven DES workflow (builder, inspector, visualizer, bottleneck, CPD, adaptor and evaluator agents) and evaluates it through 21 researcher-run experimental runs on two industrial production-line cases (Sec. 4.4, Sec. 5). Validation-research is chosen over evaluation-research because the workflow was not deployed in operational use by practitioners. The paper states: "Implementing the suggested changes in production fell outside the scope of this study" (Fig. 1 caption). Case B also used "a simplified mock-up event log", and the CPDs were fictitious (Sec. 4.2). Evaluation was through repeated experiments plus comparison against FACTS Analyzer models. Uncertainty (?): the cases come from a real company (Scania) and real MES data was used for Case A, so a reviewer could argue for evaluation-research under the 'industrial case studies' clause. | K2: The paper presents a novel LLM-driven workflow for discrete-event simulation (DES) and evaluates it using two real-world industrial case studies from a Swedish automotive manufacturer (Scania). The evaluation involves systematic analysis of 21 experimental runs, comparing generated models against commercial simulation software (FACTS Analyzer) with defined metrics (Throughput, WIP, SEC). This fits the definition of evaluation-research: 'Technique evaluated in practice (naturalistic setting: real organisation, real users, real data in operational use), incl. industrial case studies'. See Section 1 (Introduction), Section 4.2 (Use case and data collection), and Section 5 (Results). | L2: evaluation-research | M2: Case A is derived from real data, therefore industrial case study which fulfills the requirement under the clause “industrial case study” | N2: Resolved | Q2: Resolved by reviewers
A3: D002 | B3: S1 – Schmitt et al. (2026) | C3: study_characterization | D3: study_characterization.industry_sector Type: str Industry sector as reported. NR if absent. | E3: free-text | F3: Low | G3: Case/whitespace only | H3: Automotive manufacturing | I3: Automotive Manufacturing | J3: The cases come from "a large Swedish automotive manufacturer" (Sec. 1, Sec. 4.2). The affiliations name Scania CV AB. | K3: The paper explicitly states that the case studies are from 'a large Swedish automotive manufacturer' (identified as Scania CV AB in the author affiliations and abstract). The context is 'manufacturing industries' and 'production systems'. See Section 1 (Introduction) and Section 4.2 (Use case and data collection). | L3: Automotive manufacturing | N3: Resolved | P3: Triage | Q3: No discussion needed | R3: case only
A4: D003 | B4: S1 – Schmitt et al. (2026) | C4: study_characterization | D4: study_characterization.case_study_domain Type: str Case study domain as reported. NR if absent. | E4: free-text | F4: Medium | G4: Text differs (similarity 25%) | H4: Discrete-event simulation of production lines for capacity and energy-efficiency assessment (Case A: an automated machining line with 4 serial operations; Case B: an automated assembly line with 7 operations including parallel presses) | I4: Discrete-Event Simulation (DES) in Manufacturing | J4: Sec. 4.4 and Sec. 5 describe "an automated assembly line and an automated machining line". Sec. 5.3 describes Case A as four sequential operations. Sec. 5.4 describes Case B as seven machines with two parallel presses. The KPIs were TH, WIP and SEC (Sec. 4.2). | K4: The core domain is the automation of Discrete-Event Simulation (DES) modeling for manufacturing systems. The specific application areas are capacity analysis, energy efficiency assessment, and bottleneck identification in production lines (machining and assembly). See Abstract and Section 2.2 (Manufacturing system simulation). | L4: Discrete-event simulation of production lines for capacity and energy-efficiency assessment (Case A: an automated machining line with 4 serial operations; Case B: an automated assembly line with 7 operations including parallel presses) | N4: Resolved | P4: Triage | Q4: No discussion needed | R4: R2 generic, R1 specific as reported; not used for coding
A5: D004 | B5: S1 – Schmitt et al. (2026) | C5: strategic_planning_scope | D5: strategic_planning_scope.vdi5200_phase Type: list[VDI5200Phase] VDI 5200 factory planning phase(s) the method supports, pick all applicable. 'NA' (exclusive) iff 'factory-planning' is not in subdomain. Types: - 1-setting-of-objectives: Phase 1: Zielfestlegung (setting of objectives) - 2-project-basis: Phase 2: Grundlagenermittlung (establishment of the project basis) - 3-concept-planning: Phase 3: Konzeptplanung (concept planning: structure, dimensioning, layout variants) - 4-detailed-planning: Phase 4: Detailplanung (detailed planning) - 5-preparation-for-realization: Phase 5: Realisierungsvorbereitung (preparation for realization, tenders) - 6-realization-supervision: Phase 6: Realisierungsueberwachung (realization supervision) - 7-ramp-up-support: Phase 7: Hochlaufbetreuung (ramp-up support) - NA: Not a factory planning study | E5: multi-select | F5: High | G5: Only R1: 4-detailed-planning | H5: 3-concept-planning; 4-detailed-planning | I5: 3-concept-planning | J5: VDI 5200 is not referenced. The method evaluates line variants via simulation: structural changes such as adding a parallel station, and buffer dimensioning (Sec. 4.3.3). This fits concept-planning dimensioning and variant evaluation as well as detailed-planning parameter refinement. The mapping is uncertain (?) because the study concerns improvement of existing lines rather than a new factory planning project. Implementation in production is explicitly out of scope (Fig. 1 caption). | K5: The method supports evaluating different configurations (e.g., buffer sizes, parallel stations) to determine the best improvement. This is a conceptual evaluation of system variants, aligning with VDI 5200 Phase 3 (Konzeptplanung). It is not Phase 4 (Detailplanung) as it doesn't produce detailed engineering drawings or specific component specs, nor Phase 1/2 as the objectives and basis are already defined by the case studies. | L5: 3-concept-planning; 4-detailed-planning | N5: Resolved | Q5: Resolved by reviewers
A6: D005 | B6: S1 – Schmitt et al. (2026) | C6: strategic_planning_scope | D6: strategic_planning_scope.planning_horizon_tiers Type: list[PlanningHorizonTier] Reviewer-judged planning horizon tiers for which the paper's method produces or supports a decision, pick all applicable; tiers only mentioned as context do not count. 'NA' only if no tier is addressed. Strategic is selected iff system_configuring_decision is true. Types: - NA: No planning horizon addressed - Strategic: Strategic planning horizon (system configuration: what exists); set iff system_configuring_decision - Tactical: Tactical planning horizon (mid-term allocation of existing resources) - Operational: Operational planning horizon (short-term scheduling and control) | E6: multi-select | F6: High | G6: Only R1: Tactical | H6: Strategic; Tactical | I6: Strategic | J6: No horizon statements appear in the paper; the tiers are reviewer judgement. Strategic: structural changes determine what exists, e.g. 'Add a third parallel press with its own pre-buffer instance' (Fig. 14) and buffer capacity increases (Fig. 7, 14). Tactical: parametric improvements of existing machines, such as availability, cycle time, MTTR and defect rate (Table 5, Table 7). The strategic tier is borderline (?) because the decisions concern line-level modification within an existing plant. | K6: The method supports decisions that configure the system structure, such as adding or removing operations (structural adaptations) and changing buffer capacities. According to the schema definition, 'Strategic' is selected iff system_configuring_decision is true. These decisions determine what exists in the system (e.g., number of parallel presses), which is a system configuration decision. | L6: Strategic; Tactical | N6: Resolved | Q6: Resolved by reviewers
A7: D006 | B7: S1 – Schmitt et al. (2026) | C7: strategic_planning_scope | D7: strategic_planning_scope.authors_claimed_tier Type: list[PlanningHorizonTier] Tier(s) the authors themselves claim to address (e.g., 'strategic planning'), regardless of the reviewer judgement in planning_horizon_tiers; 'NA' if the authors make no tier claim. Compared with planning_horizon_tiers in the analysis ('claimed strategic, actually tactical'). Types: - NA: No planning horizon addressed - Strategic: Strategic planning horizon (system configuration: what exists); set iff system_configuring_decision - Tactical: Tactical planning horizon (mid-term allocation of existing resources) - Operational: Operational planning horizon (short-term scheduling and control) | E7: categorical | F7: High | G7: Only R2: Strategic | I7: Strategic | J7: No claim found. The authors speak of 'decision support', 'process improvements' and 'scenario exploration' but do not label the work strategic, tactical or operational. | K7: The authors frame the work as supporting 'decision support' for 'process improvements' and 'capacity and energy efficiency assessments' (Abstract, Section 1). They discuss 'brownfield' cases and 'conceptual greenfield models' (Section 6.3), implying a focus on optimizing existing or near-term configurations. While they don't explicitly use the word 'strategic', the nature of the tasks (structural changes like adding machines) aligns with the strategic tier of system configuration in the context of the schema's definitions. | N7: Resolved | Q7: Resolved by reviewers
A8: D007 | B8: S1 – Schmitt et al. (2026) | C8: strategic_planning_scope | D8: strategic_planning_scope.system_configuring_decision_stated Type: bool True only if the authors themselves frame the decision as configuring or designing the system (what exists); a verbatim quote is required in the reasoning. Default False if no such statement exists. Can only be true if system_configuring_decision is true. | E8: boolean | F8: High | G8: R1 FALSE vs R2 TRUE | H8: FALSE | I8: TRUE | J8: No statement found that frames the decision as designing or configuring the system. The authors describe 'adaptations' of simulation models and 'process improvements' (Sec. 4.3.3) for 'decision support'. | K8: Section 4.3.3 states: 'Adaptations fall into one of three 'complexity' levels; ... (ii) intermediate complexity for structural adaptations (e.g., adding or removing operations)'. Section 5.4.3 describes implementing a suggestion to 'Add a third parallel press'. This explicitly frames the decision as configuring the system structure. | L8: FALSE | N8: Resolved | Q8: Resolved by reviewers
A9: D008 | B9: S1 – Schmitt et al. (2026) | C9: strategic_planning_scope | D9: strategic_planning_scope.system_configuring_decision_description Type: str | None Free-text description, if system_configuring_decision is true, of what the decision determines (entities created, capacities set, locations chosen), as reported. | E9: free-text | F9: Medium | G9: Text differs (similarity 3%) | H9: Evaluation of line modifications: adding a third parallel press with a pre-buffer (Case B) and changing buffer capacities around bottlenecks (Cases A and B), assessed on throughput, WIP and specific energy consumption. | I9: The decision determines the structural configuration of the production line, including the number of parallel machines (e.g., adding a third press), buffer capacities, and machine availability settings. | L9: Evaluation of line modifications: adding a third parallel press with a pre-buffer (Case B) and changing buffer capacities around bottlenecks (Cases A and B), assessed on throughput, WIP and specific energy consumption. | N9: Resolved | P9: Triage | Q9: Moot – follows resolved field | R9: system-configuring not stated (= R1); R2 wording frames it as stated (D007)
A10: D009 | B10: S1 – Schmitt et al. (2026) | C10: llm_intervention | D10: llm_intervention.intervention_description Type: str Free-text description of the role the LLM/agent system plays in the planning task: inputs, outputs, and decision support function as reported. | E10: free-text | F10: Medium | G10: Text differs (similarity 2%) | H10: An end-to-end LLM-driven workflow, implemented with Python scripts and several fixed LLM API calls, automates discrete-event simulation (DES) modeling for capacity and energy-efficiency assessment of manufacturing lines. Input data (MES event logs, power ratings, defects, critical process definitions (CPDs), production calendar) are first pre-processed with static Python code and PM4Py, without an LLM. The LLM roles are: - Builder-agent (GPT-5.1): adapts a generic SimPy blueprint model into an executable current-state Python simulation model, using the structured production parameters and natural-language instructions. - Inspector-agent: verifies and repairs the generated code. - Visualizer-agent (GPT-5-mini): translates the Python model into Mermaid/JavaScript flow charts for visual inspection. - Bottleneck-agent (GPT-4o, structured JSON output): turns the utilization-based bottleneck ranking into improvement suggestions. - CPD-agent (GPT-5-mini): checks the suggestions against CPD constraints and issues warnings. - Adaptor-agent (GPT-5-mini, one instance per suggestion): produces N adapted models, each checked and repaired by the inspector-agent. - Evaluator-agent (GPT-5-mini): compares the KPIs (throughput, WIP, specific energy consumption) of the baseline and adapted models and writes textual decision-support recommendations with trade-offs. Human-in-the-loop checkpoints are: mandatory inspection and repair of the initial model, an optional extra improvement suggestion, and mandatory verification of the results. The workflow was evaluated over 21 runs on two real automotive production lines (Case A: 10 runs; Case B: 11 runs). Validation compared outputs against FACTS Analyzer models. | I10: The LLM system automates the end-to-end workflow of discrete-event simulation (DES) modeling in manufacturing. It generates executable Python simulation code (using SimPy) from heterogeneous production data (event logs, machine metrics, part-flow logic) and a blueprint model. It then adapts these models based on bottleneck analysis and human suggestions, checks for constraint violations (CPDs), and evaluates simulation outcomes (Throughput, WIP, SEC) to provide decision support. The workflow involves multiple specialized LLM roles (builder, inspector, visualizer, bottleneck, CPD, adaptor, evaluator) operating in a fixed pipeline with human-in-the-loop checkpoints. | L10: An end-to-end LLM-driven workflow, implemented with Python scripts and several fixed LLM API calls, automates discrete-event simulation (DES) modeling for capacity and energy-efficiency assessment of manufacturing lines. Input data (MES event logs, power ratings, defects, critical process definitions (CPDs), production calendar) are first pre-processed with static Python code and PM4Py, without an LLM. The LLM roles are:- Builder-agent (GPT-5.1): adapts a generic SimPy blueprint model into an executable current-state Python simulation model, using the structured production parameters and natural-language instructions.- Inspector-agent: verifies and repairs the generated code.- Visualizer-agent (GPT-5-mini): translates the Python model into Mermaid/JavaScript flow charts for visual inspection.- Bottleneck-agent (GPT-4o, structured JSON output): turns the utilization-based bottleneck ranking into improvement suggestions.- CPD-agent (GPT-5-mini): checks the suggestions against CPD constraints and issues warnings.- Adaptor-agent (GPT-5-mini, one instance per suggestion): produces N adapted models, each checked and repaired by the inspector-agent.- Evaluator-agent (GPT-5-mini): compares the KPIs (throughput, WIP, specific energy consumption) of the baseline and adapted models and writes textual decision-support recommendations with trade-offs.Human-in-the-loop checkpoints are: mandatory inspection and repair of the initial model, an optional extra improvement suggestion, and mandatory verification of the results. The workflow was evaluated over 21 runs on two real automotive production lines (Case A: 10 runs; Case B: 11 runs). Validation compared outputs against FACTS Analyzer models. | N10: Resolved | P10: Triage | Q10: No discussion needed | R10: paraphrases of the same content; narrative field, no categorical impact
A11: D010 | B11: S1 – Schmitt et al. (2026) | C11: llm_intervention | D11: llm_intervention.model_usage_context Type: str | None Free-text elaboration of which model is used for what, when multiple models are reported. | E11: free-text | F11: Medium | G11: Text differs (similarity 5%) | H11: GPT-5.1 handles the most demanding tasks: model generation (builder-agent) and the inspector-agent for the initial model. GPT-5-mini handles the cost-efficient tasks: flow-chart conversion (visualizer-agent), model adaptations (adaptor-agent and inspector-agent), CPD checking and the evaluation summaries (evaluator-agent). GPT-4o generates the JSON improvement instructions from the bottleneck analysis (bottleneck-agent) because it supports structured output. | I11: GPT-5.1 is used for the most complex tasks, specifically generating the initial simulation model (builder-agent) and inspecting/repairing it (inspector-agent). GPT-5-mini is used for simpler tasks such as converting models to flow charts (visualizer-agent), implementing adaptations (adaptor-agent), and generating summaries (evaluator-agent, CPD-agent). GPT-4o is used for generating JSON instructions from bottleneck analysis (bottleneck-agent) due to its structured output capability. | L11: GPT-5.1 handles the most demanding tasks: model generation (builder-agent) and the inspector-agent for the initial model. GPT-5-mini handles the cost-efficient tasks: flow-chart conversion (visualizer-agent), model adaptations (adaptor-agent and inspector-agent), CPD checking and the evaluation summaries (evaluator-agent). GPT-4o generates the JSON improvement instructions from the bottleneck analysis (bottleneck-agent) because it supports structured output. | N11: Resolved | P11: Triage | Q11: No discussion needed | R11: paraphrases of the same content; narrative field, no categorical impact
A12: D011 | B12: S1 – Schmitt et al. (2026) | C12: evaluation_and_outcomes | D12: evaluation_and_outcomes.evaluation_paradigm Type: EvaluationParadigm Artificial vs. naturalistic evaluation (FEDS); 'NA' iff study_design is 'none'. Types: - artificial: All evaluation episodes are artificial - naturalistic: All evaluation episodes are naturalistic - both: Both artificial and naturalistic episodes - NA: No evaluation (study_design is 'none') | E12: categorical | F12: High | G12: Only R1: both | Only R2: naturalistic | H12: both | I12: naturalistic | J12: Classification is uncertain ('?'). Case A uses real MES event logs from a real production line, with power estimated from supplier specifications (Sec. 4.2), which leans naturalistic. Case B uses a simplified mock-up event log and part-flow logic so the data could be shared. The CPDs for both cases were fictitious and created with a company simulation expert (Sec. 4.2), which is artificial. All runs were executed by the authors rather than by real end users in operations, which also pushes toward artificial. Coded 'both' to reflect real-system data (Case A) alongside mock-up/fictitious inputs (Case B, CPDs). | K12: The evaluation uses 'real-world production lines' and 'heterogeneous production data' from a 'large Swedish automotive manufacturer' (Abstract, Section 4.2). The cases are described as actual production scenarios, not simulated or invented data for the purpose of the test itself (though the simulation models are built from this data). This aligns with the 'naturalistic' paradigm (real users, real problem, real organisation/system). | L12: both | N12: Resolved | Q12: Resolved by reviewers
A13: D012 | B13: S1 – Schmitt et al. (2026) | C13: evaluation_and_outcomes | D13: evaluation_and_outcomes.dataset_or_benchmark Type: str Dataset or benchmark name and size as reported. NR if absent. | E13: free-text | F13: Medium | G13: Text differs (similarity 2%) | H13: Two industrial case datasets from a Swedish automotive manufacturer: Case A (MES event logs for a 4-machine serial machining line) and Case B (simplified mock-up event log for a 7-station assembly line with parallel presses; shared on GitHub) | I13: NR | J13: Sec. 4.2 and Sec. 5.3.1/5.4.1 describe the data sources. No public benchmark was used. Case B data is available at github.com/thomasschmitt1993/LLM-DES-Modeling. Table 2 SWE-bench values are cited only to motivate model selection; they are not used to evaluate this method. | K13: The paper uses proprietary industrial data from Scania CV AB (event logs, MES data) for two specific production lines. It does not reference a public dataset or benchmark name (e.g., SWE-bench is mentioned only for LLM capability comparison in Table 2, not as the evaluation dataset for the simulation workflow). The data is described as 'heterogeneous production data' and 'event logs' but not named as a specific public benchmark. | L13: Two industrial case datasets from a Swedish automotive manufacturer: Case A (MES event logs for a 4-machine serial machining line) and Case B (simplified mock-up event log for a 7-station assembly line with parallel presses; shared on GitHub) | N13: Resolved | P13: Triage | Q13: Moot – follows resolved field | R13: evaluation_framework_type consensus includes custom-test-set → "NR" contradicts it
A14: D013 | B14: S1 – Schmitt et al. (2026) | C14: record | D14: n_reported_metrics Number of reported metrics (one row each on the reported_metrics sheet). | E14: categorical | F14: High | G14: Only R1: 15 | Only R2: 12 | H14: 15 | I14: 12 | J14: Values are taken from Tables 5, 7, 8 and 9, Figs. 6, 9, 13, 16 and 18, and Secs. 5.3 to 5.6. The SEC percentage labels in the figure transcriptions are partly inconsistent (e.g., V2 Case B SEC shown as -5.4% and -6.4%, while the evaluator text states ~6.3%), so that SEC value is omitted. The Fig. 18 percentages were read from the bar chart. | K14: Metrics were extracted from Section 5.6 (validation deviations), Table 5 and Table 7 captions (cost, time, tokens). The paper reports KPIs (TH, WIP, SEC) for the simulation models themselves (e.g., Fig 6, Fig 13), but the primary evaluation metrics for the *method's* performance are the deviations from the ground truth (FACTS Analyzer) and the efficiency metrics (cost/time). The KPI values of the simulation models are outputs of the simulation, not metrics of the LLM framework's accuracy per se, though they are reported. I included the deviation metrics as they directly evaluate the LLM's output quality against a comparator. | L14: 15 | N14: Resolved | Q14: Resolved by reviewers
A15: D014 | B15: S1 – Schmitt et al. (2026) | C15: evaluation_and_outcomes | D15: evaluation_and_outcomes.sample_size Type: str Number of test cases, users, or records as reported. NR if absent. | E15: free-text | F15: Medium | G15: Text differs (similarity 78%) | H15: 2 production cases; 21 experimental workflow runs (10 for Case A, 11 for Case B) | I15: 21 experimental runs (10 for Case A, 11 for Case B) | J15: Stated in the abstract and in Sec. 5 and 5.5. Simulation replications (25 for Case A, 10 for Case B) are a separate quantity and refer to stochastic simulation runs, not LLM evaluation items. | K15: The Abstract states '21 experimental runs'. Section 5.3.4 mentions 'ten experiments' for Case A. Section 5.4.4 mentions 'eleven experiments' for Case B. 10 + 11 = 21. | L15: 2 production cases; 21 experimental workflow runs (10 for Case A, 11 for Case B) | N15: Resolved | P15: Triage | Q15: No discussion needed | R15: R1 contains all R2 counts (superset)
A16: D015 | B16: S1 – Schmitt et al. (2026) | C16: evaluation_and_outcomes | D16: evaluation_and_outcomes.repeated_runs Type: Annotated[int, FieldInfo(annotation=NoneType, required=True, metadata=[Ge(ge=1)])] | Literal['NR'] Number of repeated runs per test item/case used to capture LLM output variability (1 if explicitly a single run). NR if not reported. | E16: categorical | F16: High | G16: Only R1: 10 | Only R2: 21 | H16: 10 | I16: 21 | J16: Repeated runs: the full LLM workflow was executed 10 times on Case A and 11 times on Case B to capture output variability (Tables 5 and 7). The minimum of 10 is coded because the schema requires a single integer. LLM-as-judge: the inspector and evaluator agents are components of the method itself; the method's outputs were judged by the authors and the human-in-the-loop, not by an LLM. Efficiency: tokens, API cost and execution time are reported (Table 5 and 7 captions). Statistical testing: input-output validation against FACTS Analyzer used means and 95% confidence intervals from independent replications (Sec. 4.4, 5.6). No hypothesis tests were reported. | K16: Repeated runs: 21 total runs across two cases. LLM as judge: The 'evaluator-agent' interprets results, but the *evaluation of the framework's validity* is done by comparing against FACTS Analyzer (conventional method) and human inspection, not by an LLM scoring the LLM's performance against a ground truth in a meta-evaluation sense. However, the 'evaluator-agent' is part of the workflow. The schema asks if an LLM scores/judges the *outputs of the paper's method*. The paper's method *is* the workflow. The evaluation of the workflow's success is based on code correctness (human/inspector agent) and KPI deviation (comparison to FACTS). The 'evaluator-agent' is a component of the system being tested, not an external judge of the system's validity. Therefore, false. Efficiency: True, cost and time are reported in Table 5/7 captions. Statistical testing: True, Section 5.6 mentions '95% confidence intervals' and 'statistical testing' is suggested in the evaluator output (Fig 10/17) and validation criteria mention confidence intervals. | L16: 10 for Case A, 11 for Case B | N16: Resolved | O16: should be free-text answer because reference to test case is needed | P16: R1+R2 | Q16: Re-coded v0.10.0 | R16: v0.10.0: free text (D015); per-case counts as reported in Tables 5 and 7
A17: D016 | B17: S1 – Schmitt et al. (2026) | C17: evaluation_and_outcomes | D17: evaluation_and_outcomes.reported_limitations Type: list[str] 1-3 sentence paraphrase of author-stated limitations. Empty list if none are stated (= NR). | E17: free-text | F17: Medium | G17: Text differs (similarity 19%) | H17: The tested cases were relatively simple (a serial line and a line with one parallel station), so generalizability to complex systems with multiple variants and interdependent flows remains unvalidated.; Output consistency and reproducibility are limited: model generation was error-prone, especially structural split/merge errors in Case B, and required human checks and manual corrections.; Whether the approach reduces overall modeling time was not assessed, and there was no comparison against manual modeling or established ASMG approaches.; Multi-agent configurations and hyperparameter sensitivity (e.g., temperature) were not systematically evaluated; default API parameters were used.; Generating C++/XML code for commercial tools such as FACTS Analyzer performed poorly in early experiments, likely due to training-data bias toward Python.; Input data ingestion was partly manual (buffer capacities, process logic), and the CPDs and Case B data were fictitious or simplified mock-ups. | I17: Output consistency and generalizability to more complex manufacturing systems remain challenges.; The cases tested were relatively simple (sequential or simple parallel), and generalizability to complex part flows and multiple variants is unvalidated.; Certain input data (buffer capacities, process logic) had to be added manually, limiting full automation of data ingestion. | J17: Drawn from Sec. 6.4 (Limitations and future research), the Conclusion, and Sec. 4.2 for the mock-up and fictitious data. | K17: Section 6.4 ('Limitations and future research') explicitly states: 'the generalizability of the proposed approach to more complex production scenarios remains to be validated', 'certain information... had to be added manually', and 'limitations in output consistency were observed'. The Abstract also mentions 'current limitations of LLM-driven simulation, particularly regarding output consistency and generalizability.' | L17: The tested cases were relatively simple (a serial line and a line with one parallel station), so generalizability to complex systems with multiple variants and interdependent flows remains unvalidated.; Output consistency and reproducibility are limited: model generation was error-prone, especially structural split/merge errors in Case B, and required human checks and manual corrections.; Whether the approach reduces overall modeling time was not assessed, and there was no comparison against manual modeling or established ASMG approaches.; Multi-agent configurations and hyperparameter sensitivity (e.g., temperature) were not systematically evaluated; default API parameters were used.; Generating C++/XML code for commercial tools such as FACTS Analyzer performed poorly in early experiments, likely due to training-data bias toward Python.; Input data ingestion was partly manual (buffer capacities, process logic), and the CPDs and Case B data were fictitious or simplified mock-ups.; Output consistency and generalizability to more complex manufacturing systems remain challenges.; The cases tested were relatively simple (sequential or simple parallel), and generalizability to complex part flows and multiple variants is unvalidated.; Certain input data (buffer capacities, process logic) had to be added manually, limiting full automation of data ingestion. | N17: Resolved | P17: Triage | Q17: No discussion needed | R17: different limitation items → union kept for Tier-3 thematic coding
A18: D017 | B18: S1 – Schmitt et al. (2026) | C18: evaluation_and_outcomes | D18: evaluation_and_outcomes.outcome_summary Type: str | None Free-text narrative summary of the main results beyond isolated metrics, as reported. | E18: free-text | F18: Medium | G18: Text differs (similarity 3%) | H18: Across 21 runs on two industrial cases, the LLM workflow (GPT-5.1 builder/inspector, GPT-5-mini adaptor/visualizer/CPD/evaluator, GPT-4o bottleneck agent, with a SimPy blueprint for one-shot generation) generated executable DES models. It also proposed and implemented bottleneck-based adaptations, flagged CPD violations, and produced trade-off evaluations. Model generation was the weakest stage: 80% correct for Case A and 64% for Case B, with one crash and five manual corrections, mostly structural errors in parallel routing. Adaptation (92-97%) and evaluation (100%) were reliable. Validation against manually built FACTS Analyzer models showed deviations within the 5-10% threshold: about 4% for Case A and below 1% for Case B. Costs were about $0.13-0.16 per run and run times about 10-20 minutes. The authors conclude that the hybrid human-in-the-loop approach is feasible but limited by consistency and generalizability. | I18: The LLM-driven workflow successfully generated, adapted, and evaluated discrete-event simulation models for two manufacturing cases. The generated models showed high accuracy compared to commercial simulation software (deviations <10%, mostly <5%). The workflow demonstrated the ability to identify bottlenecks, propose improvements, check constraints, and evaluate trade-offs. However, errors occurred in model generation (especially for complex parallel structures) requiring human correction, and output consistency varied across runs. | L18: Across 21 runs on two industrial cases, the LLM workflow (GPT-5.1 builder/inspector, GPT-5-mini adaptor/visualizer/CPD/evaluator, GPT-4o bottleneck agent, with a SimPy blueprint for one-shot generation) generated executable DES models. It also proposed and implemented bottleneck-based adaptations, flagged CPD violations, and produced trade-off evaluations. Model generation was the weakest stage: 80% correct for Case A and 64% for Case B, with one crash and five manual corrections, mostly structural errors in parallel routing. Adaptation (92-97%) and evaluation (100%) were reliable. Validation against manually built FACTS Analyzer models showed deviations within the 5-10% threshold: about 4% for Case A and below 1% for Case B. Costs were about $0.13-0.16 per run and run times about 10-20 minutes. The authors conclude that the hybrid human-in-the-loop approach is feasible but limited by consistency and generalizability. | N18: Resolved | P18: Triage | Q18: No discussion needed | R18: paraphrases of the same content; narrative field, no categorical impact
A19: D018 | B19: S1 – Schmitt et al. (2026) | C19: gap_indicators | D19: gap_indicators.hitl_description Type: str | None Free-text elaboration of how the HITL pattern operates in the system, as reported. | E19: free-text | F19: Medium | G19: Text differs (similarity 21%) | H19: There are three human checkpoints. (1) Mandatory inspection and repair of the LLM-generated baseline SimPy model after the inspector-agent's check and before execution. (2) An optional step in which the operator adds an extra improvement suggestion via terminal text input, alongside the bottleneck-agent's suggestions. The operator also reviews the CPD-agent's warnings and the context-specific constraints that the LLM cannot see, such as layout, space and cost. (3) A mandatory check of the evaluator-agent's interpretation of the results, to catch hallucinations before decision support is given. | I19: The framework integrates human oversight at three key stages: (1) Mandatory inspection and repair of the generated initial simulation model; (2) Optional addition of manual improvement suggestions to the list generated by the LLM; (3) Mandatory verification of the final evaluation results and trade-offs before decision support. | L19: There are three human checkpoints.(1) Mandatory inspection and repair of the LLM-generated baseline SimPy model after the inspector-agent's check and before execution.(2) An optional step in which the operator adds an extra improvement suggestion via terminal text input, alongside the bottleneck-agent's suggestions. The operator also reviews the CPD-agent's warnings and the context-specific constraints that the LLM cannot see, such as layout, space and cost.(3) A mandatory check of the evaluator-agent's interpretation of the results, to catch hallucinations before decision support is given. | N19: Resolved | P19: Triage | Q19: No discussion needed | R19: paraphrases of the same content; narrative field, no categorical impact
A20: D019 | B20: S1 – Schmitt et al. (2026) | C20: gap_indicators | D20: gap_indicators.domain_knowledge_type Type: Annotated[list[DomainKnowledgeType], AfterValidator(func=<function <lambda> at 0x7ff41b44c670>)] | None All types of domain knowledge formalization present, required if domain_knowledge_formalization_present is true. Types: - ontology: Formal ontology: classes, relations and axioms of the domain (e.g., OWL), schema level - knowledge-graph: Knowledge graph: domain instances and their relations stored as a graph - standards-encoding: Machine-readable encoding of domain standards (e.g., VDI 5200, ISA-95, ISO 22400) - structured-schema: Non-graph metamodel or schema (e.g., JSON Schema, UML) for domain entities and constraints - relational-database: Relational database or taxonomy of domain entities and attributes - code-template: Code or model template encoding domain structure (e.g., simulation blueprint) - mathematical-model: Optimization or simulation model encoding domain structure and rules - other: Other domain knowledge formalization (specify) | E20: multi-select | F20: High | G20: Only R1: mathematical-model | H20: code-template; mathematical-model | I20: code-template | J20: code-template: the SimPy blueprint template is adapted by the builder-agent (Sec. 5.1, Appendix A). mathematical-model: DES models encoding machine performance, buffers and schedules are executed to compute TH, WIP and SEC (Sec. 4.3.2). This tag is less certain (?), since the model is itself the output generated from the template. | K20: The primary formalization is the 'blueprint model' described in Section 5.1 and Appendix A. It is a Python code template using SimPy that defines the structure of machines, buffers, and logic. This fits the definition of 'code-template: Code or model template encoding domain structure (e.g., simulation blueprint)'. While CPDs are mentioned, they are provided as text instructions rather than a formal ontology or KG. | L20: code-template; mathematical-model | N20: Resolved | Q20: Resolved by reviewers
A21: D020 | B21: S1 – Schmitt et al. (2026) | C21: gap_indicators | D21: gap_indicators.domain_knowledge_description Type: str | None Free-text elaboration of what domain knowledge is formalized and how, as reported. | E21: free-text | F21: Medium | G21: Text differs (similarity 5%) | H21: The generic SimPy blueprint contains functions for: - production schedules - merger and splitter processes at parallel stations - part generation and movement - DelayBuffer and Machine classes with availability, MTTR, power ratings and defect rates - exponential failure distributions - KPI calculation It serves as a one-shot example. Structured parameter tables derived from MES event logs, with part flow obtained via PM4Py process mining, are also inserted into the prompts. | I21: The system uses a Python-based 'blueprint model' (SimPy code) that serves as a one-shot example for the LLM. This template encodes the standard structure for discrete-event simulation in manufacturing, including machine classes, buffer definitions, part generation logic, and KPI calculation methods. It ensures the generated code follows a consistent, executable pattern. | L21: The generic SimPy blueprint contains functions for:- production schedules- merger and splitter processes at parallel stations- part generation and movement- DelayBuffer and Machine classes with availability, MTTR, power ratings and defect rates- exponential failure distributions- KPI calculationIt serves as a one-shot example. Structured parameter tables derived from MES event logs, with part flow obtained via PM4Py process mining, are also inserted into the prompts. | N21: Resolved | P21: Triage | Q21: Moot – follows resolved field | R21: description follows consensus type (= R1) (D019)
A22: D021 | B22: S1 – Schmitt et al. (2026) | C22: gap_indicators | D22: gap_indicators.evaluation_framework_type Type: Annotated[list[EvaluationFrameworkType], AfterValidator(func=<function <lambda> at 0x7ff41b44c670>)] | None All framework elements used, required if evaluation_framework_used is true. Code both the test instrument (benchmark, custom test set, expert ground truth) and the scoring (rubric, domain-specific metric). Types: - benchmark: Public, standardised benchmark reused from prior work - custom-test-set: Test items or cases built by the authors for this paper - expert-ground-truth: Outputs compared with expert or practitioner decisions - rubric: Graded scoring scale or criteria (incl. Likert ratings, ordinal suitability levels) - domain-specific-metric: Metric defined by the planning domain (e.g., throughput, space utilisation, cost); not generic accuracy/F1 - other: Other evaluation framework (specify) | E22: multi-select | F22: High | G22: Only R1: custom-test-set | H22: custom-test-set; expert-ground-truth; domain-specific-metric | I22: expert-ground-truth; domain-specific-metric | J22: custom-test-set: two industrial case studies were built by the authors and run repeatedly. expert-ground-truth: LLM-generated models are compared with expert-built FACTS Analyzer reference models, and the workflow was validated with a company simulation expert (Sec. 4.4). domain-specific-metric: throughput, WIP and SEC deviations are used as metrics (Tables 8 and 9). | K22: 1. 'expert-ground-truth': Section 5.6 states: 'Validation included the comparison of the results of the generated models against equivalent models built in FACTS Analyzer simulation software.' These manually built models serve as the ground truth. 2. 'domain-specific-metric': The evaluation uses manufacturing-specific KPIs: 'Throughput (TH)', 'Work-in-process (WIP)', and 'Specific Energy Consumption (SEC)' (Section 4.2). | L22: custom-test-set; expert-ground-truth; domain-specific-metric | N22: Resolved | Q22: Resolved by reviewers
A23: D022 | B23: S1 – Schmitt et al. (2026) | C23: gap_indicators | D23: gap_indicators.evaluation_framework_description Type: str | None Free-text elaboration of the evaluation framework and its application, as reported. | E23: free-text | F23: Medium | G23: Text differs (similarity 3%) | H23: Ten runs were performed for Case A (4-station serial machining line) and eleven for Case B (7-station assembly line with parallel presses). For each run, the authors recorded: - model generation success, manual correction or failure, and the error type (structural, parametric, scheduling) - correctness of BT suggestions and CPD flagging - success of the adaptations - correctness of the evaluator interpretation Accuracy per stage is summarized in Fig. 18: generation 80% and 64%, adaptation 92% and 97%, evaluation 100% for Case A and Case B respectively. Tokens, cost and execution time were also reported. Input-output validation compared the first run of each case with FACTS Analyzer models. Deviations were within 10%: about -4% TH and about 4% WIP for Case A, and under 1% for Case B. | I23: The evaluation involves running the LLM-generated simulation models and comparing their Key Performance Indicators (Throughput, WIP, SEC) against manually built models in commercial software (FACTS Analyzer). The comparison uses means and 95% confidence intervals over multiple replications. A model is considered valid if deviations are within a 5-10% threshold and no systematic bias is detected. Additionally, code correctness and LLM accuracy (hallucinations, logic errors) are tracked across 21 experimental runs. | L23: Ten runs were performed for Case A (4-station serial machining line) and eleven for Case B (7-station assembly line with parallel presses). For each run, the authors recorded:- model generation success, manual correction or failure, and the error type (structural, parametric, scheduling)- correctness of BT suggestions and CPD flagging- success of the adaptations- correctness of the evaluator interpretationAccuracy per stage is summarized in Fig. 18: generation 80% and 64%, adaptation 92% and 97%, evaluation 100% for Case A and Case B respectively. Tokens, cost and execution time were also reported.Input-output validation compared the first run of each case with FACTS Analyzer models. Deviations were within 10%: about -4% TH and about 4% WIP for Case A, and under 1% for Case B. | N23: Resolved | P23: Triage | Q23: Moot – follows resolved field | R23: description follows consensus type (= R1) (D021)
A24: D023 | B24: S1 – Schmitt et al. (2026) | C24: quality_appraisal | D24: quality_appraisal.q4_positioning_against_prior_work Type: AppraisalAnswer Q4: Is the contribution compared against existing solutions with explicit differentiation? Types: - Yes: Criterion fully met - Partially: Criterion partly met - No: Criterion not met | E24: categorical | F24: High | G24: Only R1: Partially | Only R2: Yes | H24: Partially | I24: Yes | J24: Sec. 3 reviews ASMG approaches and LLM-simulation work (Jackson et al., Obinwanne & Feng, Dengler et al., Giabbanelli et al.). It differentiates the contribution as the first end-to-end workflow with structured data inputs (Sec. 6: 'no studies have demonstrated and validated a complete end-to-end workflow'). However, there is no empirical comparison against existing ASMG or LLM approaches, which the authors themselves list as future work. | K24: Section 3 (Related Works) reviews prior work on simulation automation and LLMs in manufacturing. It specifically cites studies like Jackson et al. [4] and Obinwanne and Feng [35] that demonstrated LLMs for simple DES generation, and explicitly states that this study addresses the gap by presenting a 'complete end-to-end workflow spanning model generation, adaptation, and evaluation' which prior studies had not demonstrated and validated. Section 6.1 further contrasts this work with earlier proof-of-concepts. | L24: Partially | N24: Resolved | Q24: Resolved by reviewers
A25: D024 | B25: S1 – Schmitt et al. (2026) | C25: quality_appraisal | D25: quality_appraisal.prompts_disclosed Type: PromptDisclosure How completely the prompts are disclosed. Types: - full: All prompts/templates given verbatim (in paper, appendix or repository) - partial: Some prompts, excerpts or a paraphrase of the prompt structure - none: Prompts not disclosed | E25: categorical | F25: High | G25: Only R1: full | Only R2: partial | H25: full | I25: partial | J25: Model version: the paper names GPT-4o, GPT-5-mini and GPT-5.1 but gives no snapshot or date identifiers, so not reported. Prompts: builder and adaptor prompts appear verbatim in Appendix B, and the paper states that all prompts and LLM calls are in the GitHub repo (github.com/thomasschmitt1993/LLM-DES-Modeling), so 'full'. Decoding parameters: Fig. 2 states 'All LLMs were executed using their default API parameters' with no explicit temperature, top_p or seed values, so false. Code: available on GitHub. Data: only Case B mock-up data is shared ('input data for Case B is available'); Case A industrial data is not, so false (partially available). Run date: only 'At the time of the experiments, GPT-5.1 was the best-performing' is given, with no explicit date or period. | K25: Model versions: The paper specifies 'GPT-4o', 'GPT-5-mini', and 'GPT-5.1' but does not provide specific snapshot dates or version hashes (e.g., 'gpt-4o-2024-08-06'), so model_version_reported is false. Prompts: Appendix B provides examples of prompts for the builder and adaptor agents, but not all prompts for every agent (e.g., inspector, evaluator, CPD) are fully disclosed verbatim, so prompts_disclosed is 'partial'. Decoding params: The paper states 'All LLMs were executed using their default API parameters' (Section 4.3, Fig 2 caption) but does not list the specific values for temperature, top-p, etc., so decoding_params_reported is false. Code: A GitHub link is provided (https://github.com/thomasschmitt1993/LLM-DES-Modeling) and stated as available, so code_available is true. Data: The paper states 'input data for Case B is available at Github' (Section 4) and mentions sharing Case B-related data, so data_available is true. Run date: The paper does not specify the exact dates when the LLMs were queried, only that GPT-5.1 was the 'best-performing... at the time of the experiments', so run_date_reported is false. | L25: full | N25: Resolved | Q25: Resolved by reviewers
A26: D025 | B26: S1 – Schmitt et al. (2026) | C26: quality_appraisal | D26: quality_appraisal.data_available Type: bool True if the evaluation data/test cases are publicly available. | E26: boolean | F26: High | G26: R1 FALSE vs R2 TRUE | H26: FALSE | I26: TRUE | J26: Model version: the paper names GPT-4o, GPT-5-mini and GPT-5.1 but gives no snapshot or date identifiers, so not reported. Prompts: builder and adaptor prompts appear verbatim in Appendix B, and the paper states that all prompts and LLM calls are in the GitHub repo (github.com/thomasschmitt1993/LLM-DES-Modeling), so 'full'. Decoding parameters: Fig. 2 states 'All LLMs were executed using their default API parameters' with no explicit temperature, top_p or seed values, so false. Code: available on GitHub. Data: only Case B mock-up data is shared ('input data for Case B is available'); Case A industrial data is not, so false (partially available). Run date: only 'At the time of the experiments, GPT-5.1 was the best-performing' is given, with no explicit date or period. | K26: Model versions: The paper specifies 'GPT-4o', 'GPT-5-mini', and 'GPT-5.1' but does not provide specific snapshot dates or version hashes (e.g., 'gpt-4o-2024-08-06'), so model_version_reported is false. Prompts: Appendix B provides examples of prompts for the builder and adaptor agents, but not all prompts for every agent (e.g., inspector, evaluator, CPD) are fully disclosed verbatim, so prompts_disclosed is 'partial'. Decoding params: The paper states 'All LLMs were executed using their default API parameters' (Section 4.3, Fig 2 caption) but does not list the specific values for temperature, top-p, etc., so decoding_params_reported is false. Code: A GitHub link is provided (https://github.com/thomasschmitt1993/LLM-DES-Modeling) and stated as available, so code_available is true. Data: The paper states 'input data for Case B is available at Github' (Section 4) and mentions sharing Case B-related data, so data_available is true. Run date: The paper does not specify the exact dates when the LLMs were queried, only that GPT-5.1 was the 'best-performing... at the time of the experiments', so run_date_reported is false. | L26: partial | N26: Resolved | O26: requires adaptation to field definition: full, partially and none | P26: R1+R2 | Q26: Re-coded v0.10.0 | R26: v0.10.0: ordinal (D025); Case B input data on GitHub, Case A industrial data not shared
A27: D026 | B27: S2 – Werheid et al. (2025) | C27: bibliographic_metadata | D27: bibliographic_metadata.funding_source Type: str Funding source as reported. NR if absent. | E27: free-text | F27: Medium | G27: Text differs (similarity 79%) | H27: AIR@InnoHK research cluster of the Innovation and Technology Commission (ITC) of the HKSAR Government | I27: Innovation and Technology Commission (ITC) of the HKSAR Government | L27: AIR@InnoHK research cluster of the Innovation and Technology Commission (ITC) of the HKSAR Government | N27: Resolved | P27: Triage | Q27: No discussion needed | R27: R1 more complete (full names / grant numbers)
A28: D027 | B28: S2 – Werheid et al. (2025) | C28: bibliographic_metadata | D28: bibliographic_metadata.funding_description Type: str | None Free-text elaboration of funding context: grant numbers, funder role, or statement of no funding, as reported. | E28: free-text | F28: Medium | G28: Text differs (similarity 77%) | H28: Research funded by the AIR@InnoHK research cluster of the Innovation and Technology Commission (ITC) of the HKSAR Government, within the scope of the research project '1-5 Ramp-Up Time Reduction by Learning from Past Process Cycles'. | I28: Our research is funded by AIR@InnoHK research cluster of the Innovation and Technology Commission (ITC) of the HKSAR Government. The results presented in this paper within the scope of the research project '1-5 Ramp-Up Time Reduction by Learning from Past Process Cycles' has come to a successful completion because of the support from ITC. | L28: Research funded by the AIR@InnoHK research cluster of the Innovation and Technology Commission (ITC) of the HKSAR Government, within the scope of the research project '1-5 Ramp-Up Time Reduction by Learning from Past Process Cycles'. | N28: Resolved | P28: Triage | Q28: No discussion needed | R28: R1 more complete (full names / grant numbers)
A29: D028 | B29: S2 – Werheid et al. (2025) | C29: study_characterization | D29: study_characterization.industry_sector Type: str Industry sector as reported. NR if absent. | E29: free-text | F29: Medium | G29: Text differs (similarity 29%) | H29: Manufacturing (plastic products manufacturer; automation/assembly equipment) | I29: Manufacturing | J29: Section 3 describes the partner as 'an international manufacturer of plastic products with about 850 employees, operating six factories across three continents.' The broader domain is manufacturing automation and ramp-up (Abstract, Section 1). | K29: The paper explicitly focuses on 'manufacturing equipment selection' (Title, Abstract). The industrial partner is described in Section 3 as 'an international manufacturer of plastic products'. | L29: Manufacturing (plastic products manufacturer; automation/assembly equipment) | N29: Resolved | P29: Triage | Q29: No discussion needed | R29: R1 = R2 plus sub-sector detail
A30: D029 | B30: S2 – Werheid et al. (2025) | C30: study_characterization | D30: study_characterization.case_study_domain Type: str Case study domain as reported. NR if absent. | E30: free-text | F30: Medium | G30: Text differs (similarity 31%) | H30: Automation equipment selection (robots, feeders, vision systems) during production ramp-up planning for new products at an industrial plastic products manufacturer | I30: Automation Equipment Selection | J30: Section 3 states: 'Two automation engineers tested the system on three ramp-up planning use-cases: two for products in Europe and one in China... used to derive automation components for robots, feeders, and vision applications within the design process.' Table 1 gives examples such as pre-feeding of bushings, movement to cleaning and inspection, and visual inspection. | K30: Section 3 describes the case study as testing the system on 'ramp-up planning use-cases' to 'derive automation components for robots, feeders, and vision applications'. The abstract confirms the focus on 'streamlining equipment selection in ramp-up planning'. | L30: Automation equipment selection (robots, feeders, vision systems) during production ramp-up planning for new products at an industrial plastic products manufacturer | N30: Resolved | P30: Triage | Q30: No discussion needed | R30: R2 generic, R1 specific as reported; not used for coding
A31: D030 | B31: S2 – Werheid et al. (2025) | C31: study_characterization | D31: study_characterization.stated_research_questions Type: str Verbatim or close paraphrase of the paper's RQs. NR if none stated. | E31: free-text | F31: Medium | G31: Text differs (similarity 56%) | H31: This research investigates whether large-language models (LLMs), combined with Retrieval-Augmented Generation (RAG), can assist in streamlining equipment selection in ramp-up planning; i.e., whether factual-driven RAG-LLMs combined with a state-machine architecture can fulfill the requirements of the equipment selection process and guide automation equipment design effectively. | I31: Can large-language models (LLMs), combined with Retrieval-Augmented Generation (RAG), assist in streamlining equipment selection in ramp-up planning? | J31: No formally numbered RQs are given. The research aim is stated in the Abstract ('This research investigates whether...') and in Section 1 ('This article explores whether these recent advancements in factual-driven RAG-LLMs, combined with a state-machine architecture, can fulfill the requirements...'). These statements are presented here as a close paraphrase of an implicit RQ. | K31: The Abstract states: 'This research investigates whether large-language models (LLMs), combined with Retrieval-Augmented Generation (RAG), can assist in streamlining equipment selection in ramp-up planning.' Section 1 reiterates: 'This article explores whether these recent advancements in factual-driven RAG-LLMs, combined with a state-machine architecture, can fulfill the requirements of the equipment selection process...' | L31: This research investigates whether large-language models (LLMs), combined with Retrieval-Augmented Generation (RAG), can assist in streamlining equipment selection in ramp-up planning; i.e., whether factual-driven RAG-LLMs combined with a state-machine architecture can fulfill the requirements of the equipment selection process and guide automation equipment design effectively. | N31: Resolved | P31: Triage | Q31: No discussion needed | R31: R1 verbatim, R2 paraphrase; schema allows both
A32: D031 | B32: S2 – Werheid et al. (2025) | C32: strategic_planning_scope | D32: strategic_planning_scope.subdomain Type: list[SubdomainType] Strategic planning subdomain(s) addressed. If not stated explicitly, map by task description using Appendix A. Types: - factory-planning: Factory planning per VDI 5200 - SC-network-design: Supply chain network design - logistics-distribution-network-design: Strategic logistics and distribution network design - technology-selection: Technology selection and investment appraisal - site-selection: Site selection and facility location - GPN-design: Global production network design | E32: multi-select | F32: High | G32: Only R1: factory-planning | H32: technology-selection; factory-planning | I32: technology-selection | J32: The paper's core task is selecting automation equipment (robots, feeders, vision systems) for assembly lines during ramp-up planning (Abstract; Sec. 2). This maps most directly to technology-selection (choosing equipment and technology types and models). Factory-planning is added because the work is framed within production line design and ramp-up planning, i.e., equipment choice in the line design stage (Sec. 1: 'Automation design, especially equipment selection... The ramp-up phase relies on an effective design stage'). This is a boundary case: the scope is line or cell-level equipment selection rather than whole-factory planning, so factory-planning is marked with '?'. Investment appraisal is not performed. | K32: The paper explicitly focuses on 'automation equipment selection' (Abstract, Section 1). The system selects specific robots, feeders, and vision systems based on requirements. This aligns with 'technology-selection' (Technology selection and investment appraisal) as it involves choosing specific technical components for a production line. It is not 'factory-planning' in the broad VDI 5200 sense of layout or process design, but rather the selection of the equipment itself. Section 2 states: 'This research investigates whether large-language models (LLMs)... can assist in streamlining equipment selection'. | L32: technology-selection; factory-planning | N32: Resolved | Q32: Resolved by reviewers
A33: D032 | B33: S2 – Werheid et al. (2025) | C33: strategic_planning_scope | D33: strategic_planning_scope.planning_task_type Type: list[PlanningTaskType] Specific planning task(s) the paper's method performs, pick all applicable. Add 'other' next to listed values only if a core task of the method is not covered by them; do not add it for side aspects. Each task's subdomain (Appendix A) should appear in subdomain. Types: - requirements-elicitation: Elicitation of planning requirements - Lastenheft-generation: Generation of requirements specification (Lastenheft) - factory-layout-planning: Factory or facility layout planning - capacity-dimensioning: Dimensioning of resources/capacity within one site (machines, staff, area) - material-flow-design: Material flow design and optimization - production-system-concept-design: Concept design of the production system or line (organisation form, process chain, automation level) - warehouse-intralogistics-system-design: Design of warehouse or intralogistics systems (storage, picking, conveying technology) - simulation-modeling: Simulation modeling for planning - SC-network-configuration: Multi-echelon supply chain network configuration across suppliers, plants and distribution - logistics-distribution-network-planning: Design of the downstream logistics/distribution network (warehouses, hubs, transport links) - reverse-circular-network-design: Design of reverse-logistics, remanufacturing or circular-economy networks - supplier-sourcing-network-strategy: Supplier selection and sourcing-network strategy (single/multi-sourcing, supplier base) - facility-location: Facility location / site selection - capacity-strategy-footprint: Capacity strategy and production footprint across sites (how much capacity where) - GPN-configuration: Global production network configuration - make-or-buy: Make-or-buy decision - technology-scouting: Technology scouting and identification - investment-appraisal: Investment appraisal and evaluation - resilience-risk-scenario-planning: Resilience and risk scenario planning for network or system configuration - norm-compliance: Norm and standards compliance checking - tender-evaluation: Tender and bid evaluation - other: Other planning task not covered by standard categories (specify) | E33: multi-select | F33: High | G33: Only R1: other; production-system-concept-design | Only R2: technology-scouting | H33: other; production-system-concept-design | I33: technology-scouting | J33: Sec. 2 describes the workflow: analyse inputs -> select elementary operation -> select equipment type -> select specific equipment -> evaluate selection. This is equipment or technology selection, which none of the listed categories fully covers, so 'other' is selected. Production-system-concept-design is added tentatively ('?') because choosing the automation equipment and its type is part of line or automation concept design. Technology-scouting is not selected because the system selects from a predefined catalog rather than scouting. Requirements are provided by the user rather than elicited, although the system can request additional information after an unsuitable selection. | K33: The core task is identifying and selecting specific equipment types (robots, feeders, vision) from a catalog based on requirements. This fits 'technology-scouting' (Technology scouting and identification) or potentially 'investment-appraisal' if it included cost/benefit, but the paper emphasizes 'selection' and 'recommendations' of specific models (e.g., 'bowl feeder ZSB-N 250-30-110 by RNA'). 'technology-scouting' is the best fit for identifying the right technology/equipment. It is not 'factory-layout-planning' as the paper explicitly states in Section 3: 'it does not support layout design'. | L33: other; production-system-concept-design | N33: Resolved | Q33: Resolved by reviewers
A34: D033 | B34: S2 – Werheid et al. (2025) | C34: strategic_planning_scope | D34: strategic_planning_scope.other_planning_task_specification Type: str | None Free-text specification of the planning task. Required if 'other' was selected, otherwise null. | E34: free-text | F34: Medium | G34: Filled only by R1 | H34: Automation equipment selection: choosing the elementary operation, equipment type (e.g., SCARA robot, vibratory bowl feeder, area-scan camera) and specific supplier model for assembly processes from requirements, using a RAG-LLM copilot. | L34: Automation equipment selection: choosing the elementary operation, equipment type (e.g., SCARA robot, vibratory bowl feeder, area-scan camera) and specific supplier model for assembly processes from requirements, using a RAG-LLM copilot. | N34: Resolved | P34: Triage | Q34: Moot – follows resolved field | R34: 'other' kept in planning_task_type → specification required; only R1 filled (D032)
A35: D034 | B35: S2 – Werheid et al. (2025) | C35: strategic_planning_scope | D35: strategic_planning_scope.vdi5200_phase Type: list[VDI5200Phase] VDI 5200 factory planning phase(s) the method supports, pick all applicable. 'NA' (exclusive) iff 'factory-planning' is not in subdomain. Types: - 1-setting-of-objectives: Phase 1: Zielfestlegung (setting of objectives) - 2-project-basis: Phase 2: Grundlagenermittlung (establishment of the project basis) - 3-concept-planning: Phase 3: Konzeptplanung (concept planning: structure, dimensioning, layout variants) - 4-detailed-planning: Phase 4: Detailplanung (detailed planning) - 5-preparation-for-realization: Phase 5: Realisierungsvorbereitung (preparation for realization, tenders) - 6-realization-supervision: Phase 6: Realisierungsueberwachung (realization supervision) - 7-ramp-up-support: Phase 7: Hochlaufbetreuung (ramp-up support) - NA: Not a factory planning study | E35: multi-select | F35: High | G35: Only R1: 4-detailed-planning; 7-ramp-up-support | H35: 4-detailed-planning; 7-ramp-up-support | J35: Selecting specific equipment models (e.g., 'bowl feeder ZSB-N 250-30-110 by RNA') corresponds to detailed planning of equipment. The authors frame the work as 'equipment selection in ramp-up planning' and 'ramp-up time reduction', which suggests 7-ramp-up-support. However, they state the copilot 'does not incorporate the ramp-up implementation phase' (Sec. 3) and that it is used 'within the design process'. The ramp-up label therefore reflects the authors' framing of new product integration and is uncertain ('?'). Concept planning could also apply to equipment type selection. | K35: The subdomain is classified as 'technology-selection', not 'factory-planning'. According to the schema constraint, 'vdi5200_phase' must be 'NA' if 'factory-planning' is not in the subdomain. Although the paper discusses ramp-up planning which is related to VDI 5200 Phase 7, the primary focus is on the selection of specific equipment components (technology selection) rather than the holistic factory planning process defined by VDI 5200. | L35: 4-detailed-planning; 7-ramp-up-support | N35: Resolved | O35: because factory planning was chosen as the subdomain prior, only R1 asnwer applies | Q35: Resolved by reviewers
A36: D035 | B36: S2 – Werheid et al. (2025) | C36: strategic_planning_scope | D36: strategic_planning_scope.authors_claimed_tier Type: list[PlanningHorizonTier] Tier(s) the authors themselves claim to address (e.g., 'strategic planning'), regardless of the reviewer judgement in planning_horizon_tiers; 'NA' if the authors make no tier claim. Compared with planning_horizon_tiers in the analysis ('claimed strategic, actually tactical'). Types: - NA: No planning horizon addressed - Strategic: Strategic planning horizon (system configuration: what exists); set iff system_configuring_decision - Tactical: Tactical planning horizon (mid-term allocation of existing resources) - Operational: Operational planning horizon (short-term scheduling and control) | E36: categorical | F36: High | G36: Only R2: Strategic | I36: Strategic | J36: No claim found. The authors refer to 'ramp-up planning' and the 'design stage', but never claim a strategic, tactical or operational tier. | K36: The authors frame the work as supporting 'ramp-up planning' and 'automation design' (Section 1). While they don't use the word 'strategic', the selection of equipment for a production line is a high-level design decision. The schema maps system-configuring decisions to Strategic. The authors claim to support 'decision-making in automation equipment selection' (Abstract), which is a configuration decision. | N36: Resolved | O36: clarification: Here we look for explicit mention of the respective label | Q36: Resolved by reviewers
A37: D036 | B37: S2 – Werheid et al. (2025) | C37: strategic_planning_scope | D37: strategic_planning_scope.system_configuring_decision_description Type: str | None Free-text description, if system_configuring_decision is true, of what the decision determines (entities created, capacities set, locations chosen), as reported. | E37: free-text | F37: Medium | G37: Text differs (similarity 22%) | H37: Selection of the elementary operation, the equipment type and the specific supplier equipment model (e.g., Epson articulated arm robot C8-A1401, OPTRONIS camera, RNA bowl feeder) to be installed in assembly lines for new products. | I37: Selection of specific robot, feeder, and vision system models for a production line based on operational requirements. | L37: Selection of the elementary operation, the equipment type and the specific supplier equipment model (e.g., Epson articulated arm robot C8-A1401, OPTRONIS camera, RNA bowl feeder) to be installed in assembly lines for new products. | N37: Resolved | P37: Triage | Q37: No discussion needed | R37: paraphrases of the same content; narrative field, no categorical impact
A38: D037 | B38: S2 – Werheid et al. (2025) | C38: llm_intervention | D38: llm_intervention.intervention_description Type: str Free-text description of the role the LLM/agent system plays in the planning task: inputs, outputs, and decision support function as reported. | E38: free-text | F38: Medium | G38: Text differs (similarity 3%) | H38: A factual-driven, LLM-based copilot that supports automation engineers in selecting manufacturing automation equipment (robots, feeders, vision systems) during ramp-up planning. The user either asks general questions or states requirements for an assembly process, for example a feeding speed of 500 parts/h. A primary orchestration agent decides which subcomponents to call: an equipment selection agent, a relational (SQLite3) structured knowledge system, a semi-structured RAG knowledge system (ChromaDB), and an answer generator. The equipment selection agent runs a state-machine workflow with five steps: (1) analyse inputs, (2) select elementary operation, (3) select equipment type, (4) select specific equipment (e.g., bowl feeder ZSB-N 250-30-110 by RNA), and (5) evaluate the selection. In the evaluation step the LLM reflects on whether the choice is suitable. If it is not, the agent asks the user for more information and restarts at the elementary-operation step. The output is a traceable recommendation of specific equipment. It was tested by two automation engineers of an industrial partner on three use-cases with 47 equipment prompts: 20 suggestions were fully suitable and 24 were sufficient. | I38: The system is a factual-driven copilot designed to assist automation engineers in selecting manufacturing equipment (robots, feeders, and vision systems) during the ramp-up planning phase. It takes user-provided operational requirements as input and outputs logical, actionable equipment recommendations. The system uses a state-machine architecture to guide the decision-making process, retrieving information from both structured (relational) and semi-structured (vector) knowledge bases to ensure traceability and reduce hallucinations. | L38: A factual-driven, LLM-based copilot that supports automation engineers in selecting manufacturing automation equipment (robots, feeders, vision systems) during ramp-up planning. The user either asks general questions or states requirements for an assembly process, for example a feeding speed of 500 parts/h. A primary orchestration agent decides which subcomponents to call: an equipment selection agent, a relational (SQLite3) structured knowledge system, a semi-structured RAG knowledge system (ChromaDB), and an answer generator. The equipment selection agent runs a state-machine workflow with five steps: (1) analyse inputs, (2) select elementary operation, (3) select equipment type, (4) select specific equipment (e.g., bowl feeder ZSB-N 250-30-110 by RNA), and (5) evaluate the selection. In the evaluation step the LLM reflects on whether the choice is suitable. If it is not, the agent asks the user for more information and restarts at the elementary-operation step. The output is a traceable recommendation of specific equipment. It was tested by two automation engineers of an industrial partner on three use-cases with 47 equipment prompts: 20 suggestions were fully suitable and 24 were sufficient. | N38: Resolved | P38: Triage | Q38: No discussion needed | R38: paraphrases of the same content; narrative field, no categorical impact
A39: D038 | B39: S2 – Werheid et al. (2025) | C39: llm_intervention | D39: llm_intervention.model_usage_context Type: str | None Free-text elaboration of which model is used for what, when multiple models are reported. | E39: free-text | F39: Medium | G39: Text differs (similarity 53%) | H39: GPT-4o powers all LLM nodes: orchestrator, equipment selection agent, knowledge-system agents and answer generator. all-MiniLM-L6-v2 produces the embeddings for semi-structured retrieval in Chroma. | I39: GPT-4o is used as the core LLM for the primary orchestration agent, equipment selection agent, and answer generator. It is accessed via API through LangGraph. | L39: GPT-4o powers all LLM nodes: orchestrator, equipment selection agent, knowledge-system agents and answer generator. all-MiniLM-L6-v2 produces the embeddings for semi-structured retrieval in Chroma. | N39: Resolved | P39: Triage | Q39: No discussion needed | R39: paraphrases of the same content; narrative field, no categorical impact
A40: D039 | B40: S2 – Werheid et al. (2025) | C40: llm_intervention | D40: llm_intervention.prompting_techniques Type: list[PromptingTechnique] Prompting technique(s) used by the paper's method, pick all applicable; 'NR' (exclusive) if prompting is not described. Types: - zero-shot: Instructions only, no worked examples - few-shot: In-context examples of input/output pairs - CoT: Model is asked for intermediate reasoning steps - self-consistency: Several sampled outputs aggregated (e.g., majority vote) - ReAct: Interleaved reasoning and tool actions - structured-output: Output constrained to a schema or grammar (JSON schema, function calling) - other: Other technique (e.g., tree-of-thoughts, role prompting) (specify) - NR: Prompting not described | E40: multi-select | F40: High | G40: Only R1: zero-shot | Only R2: other; structured-output | H40: zero-shot | I40: structured-output; other | J40: Section 2 describes predefined instruction prompts ("pre-prompt") that tell the LLM how to interpret requirements, group them into component types, and synthesize answers. A "provided template" can reinforce this, but no worked input/output examples are described, so the coding is zero-shot instructions. The reflection step is coded under planning_reflection rather than as CoT, since intermediate reasoning prompting is not described. Uncertain (?) because the prompt contents are not shown. | K40: The system uses 'pre-prompt' and 'predefined prompt' to structure the interaction and guide the LLM (Section 2). It also uses a 'template' to reinforce requirements. The output is synthesized by an answer generator with a 'defined pre-prompt'. This aligns with structured prompting. The 'other' category is used for the specific 'pre-prompt' and 'template' based guidance described in Section 2, which is a form of role/task-specific prompting not strictly fitting zero/few-shot/CoT/ReAct definitions in the standard sense, but rather a structured workflow prompting. | L40: zero-shot | N40: Resolved | Q40: Resolved by reviewers
A41: D040 | B41: S2 – Werheid et al. (2025) | C41: llm_intervention | D41: llm_intervention.other_prompting_technique_specification Type: str | None Free-text specification of the prompting technique. Required if 'other' was selected, otherwise null. | E41: free-text | F41: Medium | G41: Filled only by R2 | I41: Use of predefined pre-prompts and templates to structure user input and guide LLM reasoning steps within a state machine. | L41: NA | N41: Resolved | P41: Triage | Q41: Moot – follows resolved field | R41: parent value removed/none → field structurally inapplicable (D039)
A42: D041 | B42: S2 – Werheid et al. (2025) | C42: llm_intervention | D42: llm_intervention.workflow_patterns Type: list[WorkflowPattern] All workflow patterns used inside the method, at any level of nesting; 'none' is exclusive. Types: - prompt-chaining: Fixed sequence of LLM calls, each processing the previous output - routing: An LLM call classifies the input and sends it to a specialised follow-up - parallelization: Independent LLM calls run in parallel (sectioning or voting) and are aggregated - orchestrator-workers: A central LLM breaks the task down at run time and delegates to workers - evaluator-optimizer: One LLM generates, another evaluates and feeds back, in a loop - none: None of these patterns (single call or single autonomous agent) | E42: multi-select | F42: High | G42: Only R1: prompt-chaining; routing | H42: routing; orchestrator-workers; prompt-chaining; evaluator-optimizer | I42: orchestrator-workers; evaluator-optimizer | J42: Routing and orchestrator-workers: the orchestrator decides at run time whether a query is a general question or an equipment selection request, and which knowledge subcomponents to call (Fig. 1, dashed conditional edges). Prompt-chaining: inside the equipment selection agent, fixed edges chain the steps analyse inputs → select elementary operation → select equipment type → select specific equipment → evaluate selection. Evaluator-optimizer: the evaluation step has the LLM reflect on suitability, and an unsuitable selection loops back to the elementary-operation step with additional user information (Section 2). The evaluator may be the same LLM rather than a separate one (?). | K42: The 'primary orchestration agent' delegates to subcomponents (orchestrator-workers). Section 2 describes an 'evaluation selection step, where the LLM reflects the suitability of the decision... In case of an unsuitable selection... restarting the selection'. This is an evaluator-optimizer loop (reflection and retry). | L42: routing; orchestrator-workers; prompt-chaining; evaluator-optimizer | N42: Resolved | Q42: Resolved by reviewers
A43: D042 | B43: S2 – Werheid et al. (2025) | C43: evaluation_and_outcomes | D43: evaluation_and_outcomes.study_design Type: list[StudyDesignType] All evaluation settings used for the paper's own method, pick all applicable. 'none' (exclusive) iff validation_status is framework-only or conceptual. Types: - test-set: Set of test items (public or author-built) scored against expected answers - single-case: One case (one company, line or network) worked through - multi-case: Two or more distinct cases worked through - user-study: Structured protocol (tasks, questionnaire or interviews) with participants other than the authors - quasi-experimental: Controlled comparison of conditions or groups on the same tasks - field-deployment: System in operational use, outcomes observed in practice - none: No evaluation of the paper's own method (framework-only or conceptual papers only) | E43: multi-select | F43: High | G43: Only R1: single-case; test-set | Only R2: multi-case; user-study | H43: single-case; test-set | I43: multi-case; user-study | J43: Section 3 describes one industrial partner, a plastics manufacturer with about 850 employees. Two of its automation engineers tested the copilot on three internal ramp-up planning use-cases (two in Europe, one in China). The 47 equipment prompts were scored against the partner's internal equipment selection, which fits 'test-set'. Because all use-cases come from one company, this is coded 'single-case' rather than 'multi-case'. It is not coded 'user-study' because no structured questionnaire or interview protocol is described, only feedback. The industrial partner had web access to the system for the case study (hosted on Azure, Section 2), but it was not operational deployment, so 'field-deployment' is not coded. | K43: Section 3 ('Industrial case-study') states that 'Two automation engineers tested the system on three ramp-up planning use-cases'. This constitutes a multi-case study (3 distinct use-cases) and a user-study (structured testing by specific users, the engineers, against internal selections). It is not a field-deployment as it was a demonstration/test phase, not operational use. | L43: multi-case; test-set | N43: Resolved | Q43: Fix consensus (format/schema) | R43: lower-case vocabulary term → proposed: multi-case; test-set
A44: D043 | B44: S2 – Werheid et al. (2025) | C44: evaluation_and_outcomes | D44: evaluation_and_outcomes.dataset_or_benchmark Type: str Dataset or benchmark name and size as reported. NR if absent. | E44: free-text | F44: Medium | G44: Text differs (similarity 3%) | H44: 47 equipment prompts from 3 internal ramp-up planning use-cases of the industrial partner (confidential; examples in Table 1) | I44: NR | J44: Section 3: 'Among the 47 equipment prompts analyzed...'. Only some prompts are shown in Table 1 because of confidentiality. No public benchmark was used. | K44: No public dataset or standard benchmark is mentioned. The evaluation uses internal company data and specific prompts provided by the partner (Section 3). | L44: 47 equipment prompts from 3 internal ramp-up planning use-cases of the industrial partner (confidential; examples in Table 1) | N44: Resolved | P44: Triage | Q44: Moot – follows resolved field | R44: evaluation_framework_type consensus includes custom-test-set → "NR" contradicts it
A45: D044 | B45: S2 – Werheid et al. (2025) | C45: evaluation_and_outcomes | D45: evaluation_and_outcomes.comparator Type: list[ComparatorType] Type(s) of comparator: an alternative method applied to the same task and cases as the paper's method. Not comparators: swapping the LLM backbone, ablations of the method's own components, and comparison against ground truth or observed data. Code 'none' (exclusive) if only these occur. Types: - human-planner: Humans doing the task without the system, incl. the manual pre-LLM process - conventional-method: Non-AI algorithm or tool (OR solver, heuristic, commercial software) - prior-AI-ML: Another AI/ML or LLM method, incl. prompting baselines such as plain CoT - none: No comparator used | E45: categorical | F45: High | G45: Only R1: none | Only R2: human-planner | H45: none | I45: human-planner | J45: The copilot's suggestions were compared against the partner's internal component selection (Table 1, Section 3). This selection served as the reference or ground truth for judging suitability, not as an alternative method evaluated on the same metrics. It is therefore coded 'none'. It could arguably be read as 'human-planner' ('?'). | K45: Section 3 states: 'the components suggested by the copilot were compared against the internal selection.' The 'internal selection' refers to the choices made by the automation engineers (humans) without the system, serving as the baseline/comparator. | L45: human-planner | N45: Resolved | Q45: Fix consensus (format/schema) | R45: lower-case vocabulary term → proposed: human-planner
A46: D045 | B46: S2 – Werheid et al. (2025) | C46: evaluation_and_outcomes | D46: evaluation_and_outcomes.sample_size Type: str Number of test cases, users, or records as reported. NR if absent. | E46: free-text | F46: Medium | G46: Text differs (similarity 65%) | H46: 47 equipment prompts; 3 use-cases; 2 automation engineers | I46: 47 prompts, 3 use-cases, 2 users | J46: Section 3: 'Two automation engineers tested the system on three ramp-up planning use-cases'; 'Among the 47 equipment prompts analyzed'. | K46: Section 3 explicitly states 'Among the 47 equipment prompts analyzed' and 'three ramp-up planning use-cases' tested by 'Two automation engineers'. | L46: 47 equipment prompts; 3 use-cases; 2 automation engineers | N46: Resolved | P46: Triage | Q46: No discussion needed | R46: R1 contains all R2 counts (superset)
A47: D046 | B47: S2 – Werheid et al. (2025) | C47: evaluation_and_outcomes | D47: evaluation_and_outcomes.reported_limitations Type: list[str] 1-3 sentence paraphrase of author-stated limitations. Empty list if none are stated (= NR). | E47: free-text | F47: Medium | G47: Text differs (similarity 64%) | H47: The copilot does not support layout design, which influences equipment selection itself.; The copilot does not incorporate the ramp-up implementation phase.; Not all evaluation prompts can be shown because they involve confidential company information. | I47: The system does not support layout design, which is an important aspect influencing equipment selection.; The system does not incorporate the ramp-up implementation phase. | J47: Section 3 and Section 4 state the layout design and ramp-up implementation limitations. Section 3 notes the confidentiality restriction. Future work (discrete-event simulation, MCP, data integration) is mentioned in Section 4. | K47: Section 3 ('Nevertheless, it also had certain limitations...') and Section 4 ('However, limitations remain...') explicitly state that the copilot does not address layout design or the ramp-up implementation phase. | L47: The copilot does not support layout design, which influences equipment selection itself.; The copilot does not incorporate the ramp-up implementation phase.; Not all evaluation prompts can be shown because they involve confidential company information. | N47: Resolved | P47: Triage | Q47: No discussion needed | R47: same limitation items (64% similar)
A48: D047 | B48: S2 – Werheid et al. (2025) | C48: evaluation_and_outcomes | D48: evaluation_and_outcomes.outcome_summary Type: str | None Free-text narrative summary of the main results beyond isolated metrics, as reported. | E48: free-text | F48: Medium | G48: Text differs (similarity 8%) | H48: The RAG-based, state-machine, multi-agent copilot (GPT-4o, LangGraph, ChromaDB, SQLite3) was tested by two automation engineers at a plastics manufacturer on three ramp-up use-cases. Of 47 equipment prompts, 3 got the correct type but the wrong subtype, 24 got a sufficient component (correct subtype, most requirements), and 20 got a fully suitable component meeting all requirements. The partner's feedback affirmed that the system gives logical, actionable equipment recommendations aligned with their requirements, though it does not address layout design or ramp-up implementation. | I48: The system demonstrated the capability to provide logical and actionable recommendations. Out of 47 prompts, 20 resulted in fully suitable equipment selections meeting all requirements, and 24 resulted in sufficient selections meeting most requirements. The industrial partner affirmed its capability, though it lacks support for layout design and implementation phases. | L48: The RAG-based, state-machine, multi-agent copilot (GPT-4o, LangGraph, ChromaDB, SQLite3) was tested by two automation engineers at a plastics manufacturer on three ramp-up use-cases. Of 47 equipment prompts, 3 got the correct type but the wrong subtype, 24 got a sufficient component (correct subtype, most requirements), and 20 got a fully suitable component meeting all requirements. The partner's feedback affirmed that the system gives logical, actionable equipment recommendations aligned with their requirements, though it does not address layout design or ramp-up implementation. | N48: Resolved | P48: Triage | Q48: No discussion needed | R48: paraphrases of the same content; narrative field, no categorical impact
A49: D048 | B49: S2 – Werheid et al. (2025) | C49: gap_indicators | D49: gap_indicators.hitl_type Type: Annotated[list[HITLType], AfterValidator(func=<function <lambda> at 0x7ff41b44c670>)] | None All HITL patterns present, required if hitl_pattern_present is true. Classify by who triggers the human step (workflow, human, system) and when. Types: - approval-gate: Workflow-initiated: a human must check and accept or repair output before the workflow proceeds - what-if-interface: Human-initiated: human poses scenarios or changes inputs to explore outcomes - escalation-protocol: System-initiated: the system detects uncertainty, failure or missing information and asks the human - iterative-feedback: Human judges each iteration's output and gives guidance that steers the next iteration - human-override: Human edits or vetoes the agents' intermediate decisions or plans - other: Other HITL pattern (specify) | E49: multi-select | F49: High | G49: Only R2: iterative-feedback | H49: escalation-protocol | I49: escalation-protocol; iterative-feedback | J49: The system triggers the human step. The LLM's evaluate-selection step detects an unsuitable selection and asks the user for more information (Section 2: "additional information about the decision is requested from the user"). This fits escalation-protocol. There is no explicit approval gate or override mechanism. | K49: The system initiates a request for more information when it cannot fulfill requirements or detects unsuitability (escalation-protocol). The user provides this information, which steers the next iteration of the selection process (iterative-feedback). Section 2: 'additional information about the decision is requested from the user... restarting the selection'. | L49: escalation-protocol | N49: Resolved | Q49: Resolved by reviewers
A50: D049 | B50: S2 – Werheid et al. (2025) | C50: gap_indicators | D50: gap_indicators.hitl_description Type: str | None Free-text elaboration of how the HITL pattern operates in the system, as reported. | E50: free-text | F50: Medium | G50: Text differs (similarity 7%) | H50: After a specific piece of equipment is selected, the LLM checks whether the choice is suitable. If it judges the choice unsuitable, it asks the user for additional information. The selection then restarts from the elementary-operation step, using the new input. | I50: The copilot operates as a state machine. If the LLM determines that the selected equipment is unsuitable or requirements are not fully met, it requests additional information from the user. The user provides this input, and the system restarts the selection process for the elementary operation with the new context. | L50: After a specific piece of equipment is selected, the LLM checks whether the choice is suitable. If it judges the choice unsuitable, it asks the user for additional information. The selection then restarts from the elementary-operation step, using the new input. | N50: Resolved | P50: Triage | Q50: Moot – follows resolved field | R50: description follows consensus hitl_type (= R1) (D048)
A51: D050 | B51: S2 – Werheid et al. (2025) | C51: gap_indicators | D51: gap_indicators.domain_knowledge_type Type: Annotated[list[DomainKnowledgeType], AfterValidator(func=<function <lambda> at 0x7ff41b44c670>)] | None All types of domain knowledge formalization present, required if domain_knowledge_formalization_present is true. Types: - ontology: Formal ontology: classes, relations and axioms of the domain (e.g., OWL), schema level - knowledge-graph: Knowledge graph: domain instances and their relations stored as a graph - standards-encoding: Machine-readable encoding of domain standards (e.g., VDI 5200, ISA-95, ISO 22400) - structured-schema: Non-graph metamodel or schema (e.g., JSON Schema, UML) for domain entities and constraints - relational-database: Relational database or taxonomy of domain entities and attributes - code-template: Code or model template encoding domain structure (e.g., simulation blueprint) - mathematical-model: Optimization or simulation model encoding domain structure and rules - other: Other domain knowledge formalization (specify) | E51: multi-select | F51: High | G51: Only R2: structured-schema | H51: relational-database | I51: relational-database; structured-schema | J51: Section 2 describes a relational database (SQLite3) that maps equipment to attributes, with an equipment category-to-type taxonomy (Appendix B.1). It is extendable via HTTP POST through a Swagger interface. No ontology or knowledge graph is described. | K51: The paper explicitly mentions a 'relational knowledge system' using 'SQLite3' (Section 2, Fig 1 legend). It maps equipment to attributes, which fits 'relational-database'. The mapping of equipment categories to types (Appendix B) and the structured nature of the data retrieval implies a 'structured-schema' or taxonomy, though 'relational-database' is the primary explicit implementation detail. The semi-structured RAG part is not formalized in the same way (it's vector embeddings of text chunks), so it doesn't count as formalization per the schema definition ('Free-text... unstructured RAG corpora alone do not count'). However, the relational DB part does. | L51: relational-database | N51: Resolved | Q51: Fix consensus (format/schema) | R51: lower-case vocabulary term → proposed: relational-database
A52: D051 | B52: S2 – Werheid et al. (2025) | C52: gap_indicators | D52: gap_indicators.domain_knowledge_description Type: str | None Free-text elaboration of what domain knowledge is formalized and how, as reported. | E52: free-text | F52: Medium | G52: Text differs (similarity 6%) | H52: A SQLite3 relational database maps specific equipment (robots, feeders, vision systems) to their attributes and is linked to supplier product catalogs. The mapping is based on scientific books. A taxonomy of elementary operations and equipment categories/types (e.g., SCARA, Vibratory Bowl Feeder, Area Scan Camera) is used to select the elementary operation, then the equipment type, then the specific equipment. A complementary semi-structured Markdown corpus (lecture slides, dissertations) is stored in ChromaDB for RAG. | I52: The system uses a relational database (SQLite3) to store structured knowledge mapping specific equipment (robots, feeders, vision systems) to their attributes. This is linked to product and equipment catalogs. Additionally, a semi-structured knowledge system uses RAG with ChromaDB to retrieve text chunks from lecture slides and dissertations. | L52: A SQLite3 relational database maps specific equipment (robots, feeders, vision systems) to their attributes and is linked to supplier product catalogs. The mapping is based on scientific books. A taxonomy of elementary operations and equipment categories/types (e.g., SCARA, Vibratory Bowl Feeder, Area Scan Camera) is used to select the elementary operation, then the equipment type, then the specific equipment. A complementary semi-structured Markdown corpus (lecture slides, dissertations) is stored in ChromaDB for RAG. | N52: Resolved | P52: Triage | Q52: Moot – follows resolved field | R52: description follows consensus type (= R1) (D050)
A53: D052 | B53: S2 – Werheid et al. (2025) | C53: gap_indicators | D53: gap_indicators.evaluation_framework_type Type: Annotated[list[EvaluationFrameworkType], AfterValidator(func=<function <lambda> at 0x7ff41b44c670>)] | None All framework elements used, required if evaluation_framework_used is true. Code both the test instrument (benchmark, custom test set, expert ground truth) and the scoring (rubric, domain-specific metric). Types: - benchmark: Public, standardised benchmark reused from prior work - custom-test-set: Test items or cases built by the authors for this paper - expert-ground-truth: Outputs compared with expert or practitioner decisions - rubric: Graded scoring scale or criteria (incl. Likert ratings, ordinal suitability levels) - domain-specific-metric: Metric defined by the planning domain (e.g., throughput, space utilisation, cost); not generic accuracy/F1 - other: Other evaluation framework (specify) | E53: multi-select | F53: High | G53: Only R1: rubric | H53: custom-test-set; expert-ground-truth; rubric | I53: custom-test-set; expert-ground-truth | J53: The test set is custom: 47 prompts from the partner's internal use-cases. Ground truth is expert-based, since suggestions were compared with the partner engineers' internal selections (Table 1, "Component suggested by partner"). Scoring uses ordinal suitability levels (correct type only / sufficient / fully suitable). | K53: The test cases were internal use-cases from the industrial partner (custom-test-set). The evaluation compared the copilot's suggestions against the 'internal selection' made by the partner's automation engineers (expert-ground-truth). Section 3: 'the components suggested by the copilot were compared against the internal selection.' | L53: custom-test-set; expert-ground-truth | N53: Resolved | O53: no scala identified in paper; different categories are compared | Q53: Resolved by reviewers
A54: D053 | B54: S2 – Werheid et al. (2025) | C54: gap_indicators | D54: gap_indicators.evaluation_framework_description Type: str | None Free-text elaboration of the evaluation framework and its application, as reported. | E54: free-text | F54: Medium | G54: Text differs (similarity 13%) | H54: Industrial case study with a plastics manufacturer. Two automation engineers ran 47 equipment prompts across three ramp-up use-cases (two in Europe, one in China) covering robots, feeders and vision systems. Copilot suggestions were compared to the partner's internal selections and classified as: correct equipment type but wrong subtype (3), correct subtype meeting most requirements (24), or fully suitable meeting all requirements (20). | I54: The system was evaluated using 47 equipment prompts derived from three internal ramp-up planning use-cases of an industrial partner. The outputs were compared against the partner's internal expert selections. Success was measured by whether the correct equipment type was selected, the correct subtype was identified, and whether all specific requirements were met. | L54: The system was evaluated using 47 equipment prompts derived from three internal ramp-up planning use-cases of an industrial partner. The outputs were compared against the partner's internal expert selections. Success was measured by whether the correct equipment type was selected, the correct subtype was identified, and whether all specific requirements were met. | N54: Resolved | P54: Triage | Q54: Moot – follows resolved field | R54: description follows consensus type (= R2, no rubric) (D052)
A55: D054 | B55: S2 – Werheid et al. (2025) | C55: quality_appraisal | D55: quality_appraisal.q1_methodological_transparency Type: AppraisalAnswer Q1: Is the method (study design, system architecture, or framework logic) described in enough detail for independent replication? Types: - Yes: Criterion fully met - Partially: Criterion partly met - No: Criterion not met | E55: categorical | F55: High | G55: Only R1: Partially | Only R2: Yes | H55: Partially | I55: Yes | J55: Section 2 and Fig. 1 describe the architecture in good detail. They cover the orchestrator, equipment selection agent, relational knowledge system (SQLite3), semi-structured RAG system (ChromaDB, all-MiniLM-L6-v2, chunk size 750, overlap 150, top-3 retrieval by dot product), and the LangGraph state machine with GPT-4o, Django REST, Gradio and Azure. However, the pre-prompts are not given ("based on a predefined prompt (pre-prompt)"), the knowledge sources are internal ("lecture slides and dissertations provided by the WZL institute"), and the supplier catalogs are unspecified. Independent replication would therefore be difficult. | K55: The paper provides a detailed description of the system architecture in Section 2 ('Copilot design'). It specifies the multi-agent design pattern, the state machine workflow (Fig. 1), the specific LLM used (GPT-4o), the vector database (ChromaDB) with embedding model (all-MiniLM-L6-v2), the relational database (SQLite3), and the framework (LangGraph). It also details RAG parameters such as chunk size (750) and overlap (150). Section 3 lists the specific technologies used (Django REST Framework, Gradio, Azure). This level of detail allows for independent replication of the system setup. | L55: Partially | N55: Resolved | Q55: Resolved by reviewers
A56: D055 | B56: S2 – Werheid et al. (2025) | C56: quality_appraisal | D56: quality_appraisal.q3_validity_and_limitation_discussion Type: AppraisalAnswer Q3: Are the boundaries of the contribution explicitly discussed (failure modes, scalability, external validity, domain assumptions)? Types: - Yes: Criterion fully met - Partially: Criterion partly met - No: Criterion not met | E56: categorical | F56: High | G56: Only R1: Partially | Only R2: Yes | H56: Partially | I56: Yes | J56: Sections 3 and 4 note scope limitations: "it does not support layout design" and "does not incorporate the ramp-up implementation phase." Future work is also listed. The paper does not discuss failure modes, hallucination residuals, external validity (single partner, two engineers), scalability, or evaluation bias. | K56: Section 3 explicitly states limitations: 'it does not support layout design... Additionally, it does not incorporate the ramp-up implementation phase.' Section 4 (Conclusion) reiterates these limitations and discusses future directions like discrete-event simulation integration. The authors acknowledge that the system relies on specific domain knowledge and does not cover the full ramp-up process. | L56: Partially | N56: Resolved | O56: limitations in evaluation of the study (no sensible limitations) | Q56: Resolved by reviewers
A57: D056 | B57: S2 – Werheid et al. (2025) | C57: quality_appraisal | D57: quality_appraisal.q4_positioning_against_prior_work Type: AppraisalAnswer Q4: Is the contribution compared against existing solutions with explicit differentiation? Types: - Yes: Criterion fully met - Partially: Criterion partly met - No: Criterion not met | E57: categorical | F57: High | G57: Only R1: Partially | Only R2: Yes | H57: Partially | I57: Yes | J57: Section 1 includes a Scopus/WoS search (198 and 85 articles) and briefly summarizes related LLM manufacturing works [21-26]. It identifies a gap: "no studies have been identified that propose LLM-driven methods or tools specifically designed to support automation engineers in equipment selection." It also contrasts with static rule-based methods [9,10]. There is no detailed or empirical comparison with existing solutions. | K57: Section 1 (Introduction) reviews existing methods, noting they 'often rely on static rules and predefined knowledge' and 'lack generalization'. It contrasts the proposed LLM/RAG approach with these static methods and other LLM applications in manufacturing (assembly instructions, human-robot communication). The paper explicitly states: 'no studies have been identified that propose LLM-driven methods or tools specifically designed to support automation engineers in equipment selection during the ramp-up phase.' | L57: Partially | N57: Resolved | O57: no empirical comparison | Q57: Resolved by reviewers
A58: D057 | B58: S3 – Hu et al. (2026) | C58: study_characterization | D58: study_characterization.industry_sector Type: str Industry sector as reported. NR if absent. | E58: free-text | F58: Low | G58: Case/whitespace only | H58: Discrete manufacturing | I58: Discrete Manufacturing | J58: Sec. 4.2 states: 'The method in this paper is applicable to discrete manufacturing industries...' The case study is a discrete manufacturing shopfloor producing metal parts. The dataset sources also include motor manufacturing plants, machine processing workshops and textile companies (Sec. 4.1). | K58: The abstract and introduction focus on 'modern industrial production' and 'discrete manufacturing shopfloor scenarios'. Section 4.2 specifically mentions 'discrete manufacturing shopfloor' and lists equipment such as 'CNC lathes, CNC milling machines, drilling machines, and inspection tables'. The case study involves a 'small discrete manufacturing shopfloor'. | L58: Discrete manufacturing | N58: Resolved | P58: Triage | Q58: No discussion needed | R58: case only
A59: D058 | B59: S3 – Hu et al. (2026) | C59: study_characterization | D59: study_characterization.case_study_domain Type: str Case study domain as reported. NR if absent. | E59: free-text | F59: Medium | G59: Text differs (similarity 16%) | H59: Shopfloor (facility) layout generation for a small discrete manufacturing shopfloor with CNC lathes, CNC milling machines, drilling machines and inspection tables (single production line for metal parts); I-, L- and U-shaped layouts | I59: Shopfloor Layout Design | J59: Sec. 4.2: 'This paper used a small discrete manufacturing shopfloor as a case study, which is fully equipped with CNC lathes, CNC milling machines, drilling machines, and inspection tables, with only one production line for manufacturing different types of metal parts.' Three layout patterns (double-line/I-shape, L-shape, U-shape) were tested. | K59: The entire paper is dedicated to 'Shopfloor layout generation'. Section 4.2 details the case study: 'In the context of discrete manufacturing shopfloor... this paper selected these three different layout models [I-shape, L-shape, U-shape] as the main content for the layout requirement experiments.' The domain is specifically the spatial arrangement of equipment in a manufacturing workshop. | L59: Shopfloor (facility) layout generation for a small discrete manufacturing shopfloor with CNC lathes, CNC milling machines, drilling machines and inspection tables (single production line for metal parts); I-, L- and U-shaped layouts | N59: Resolved | P59: Triage | Q59: No discussion needed | R59: R2 generic, R1 specific as reported; not used for coding
A60: D059 | B60: S3 – Hu et al. (2026) | C60: strategic_planning_scope | D60: strategic_planning_scope.vdi5200_phase Type: list[VDI5200Phase] VDI 5200 factory planning phase(s) the method supports, pick all applicable. 'NA' (exclusive) iff 'factory-planning' is not in subdomain. Types: - 1-setting-of-objectives: Phase 1: Zielfestlegung (setting of objectives) - 2-project-basis: Phase 2: Grundlagenermittlung (establishment of the project basis) - 3-concept-planning: Phase 3: Konzeptplanung (concept planning: structure, dimensioning, layout variants) - 4-detailed-planning: Phase 4: Detailplanung (detailed planning) - 5-preparation-for-realization: Phase 5: Realisierungsvorbereitung (preparation for realization, tenders) - 6-realization-supervision: Phase 6: Realisierungsueberwachung (realization supervision) - 7-ramp-up-support: Phase 7: Hochlaufbetreuung (ramp-up support) - NA: Not a factory planning study | E60: multi-select | F60: High | G60: Only R1: 4-detailed-planning | H60: 3-concept-planning; 4-detailed-planning | I60: 3-concept-planning | J60: Generating layout variants following layout patterns (I/L/U-shaped) corresponds to concept planning (ideal/real layout) (Sec. 4.2). Exact equipment coordinates, safety distances, interference ranges and maintenance space (Sec. 3.2.2, Fig. 12) extend toward fine/detailed layout planning. The assignment to Phase 4 is uncertain ('?'); the paper does not reference VDI 5200 phases. | K60: The method generates layout schemes/variants based on requirements and constraints. Section 4.2 mentions generating 'layout schemes' and comparing them. This corresponds to Phase 3 (Concept Planning) where layout variants are developed and evaluated, rather than detailed engineering (Phase 4) or realization (Phase 5/6). The paper focuses on the design/generation of the layout concept. | L60: 3-concept-planning; 4-detailed-planning | N60: Resolved | O60: see reasoning r1 | Q60: Resolved by reviewers
A61: D060 | B61: S3 – Hu et al. (2026) | C61: strategic_planning_scope | D61: strategic_planning_scope.authors_claimed_tier Type: list[PlanningHorizonTier] Tier(s) the authors themselves claim to address (e.g., 'strategic planning'), regardless of the reviewer judgement in planning_horizon_tiers; 'NA' if the authors make no tier claim. Compared with planning_horizon_tiers in the analysis ('claimed strategic, actually tactical'). Types: - NA: No planning horizon addressed - Strategic: Strategic planning horizon (system configuration: what exists); set iff system_configuring_decision - Tactical: Tactical planning horizon (mid-term allocation of existing resources) - Operational: Operational planning horizon (short-term scheduling and control) | E61: categorical | F61: High | G61: Only R2: Strategic | I61: Strategic | J61: No claim found; the authors do not use strategic/tactical/operational terminology. | K61: The authors frame the work as 'shopfloor layout design' and 'layout generation'. While they don't use the word 'strategic' explicitly in a tier sense, the task of designing the factory layout is inherently a strategic/system-configuring activity in the context of factory planning. The abstract mentions 'adaptive and customizable potential' for 'modern industrial production', implying a design-level decision. | N61: Resolved | O61: see reasoning r1; and explanaition in earlier cases for same category | Q61: Resolved by reviewers
A62: D061 | B62: S3 – Hu et al. (2026) | C62: strategic_planning_scope | D62: strategic_planning_scope.system_configuring_decision_description Type: str | None Free-text description, if system_configuring_decision is true, of what the decision determines (entities created, capacities set, locations chosen), as reported. | E62: free-text | F62: Medium | G62: Text differs (similarity 16%) | H62: Positions (2D coordinates on X/Z plane) and arrangement of preset equipment (CNC lathes, milling machines, drilling machines, inspection tables) within a shopfloor and production line. The layout follows I-, L- or U-shaped patterns while satisfying building, area and channel boundary constraints and inter-equipment constraints (safety distance, interference, maintenance space). | I62: The decision determines the 2D coordinates, dimensions, and relative positions of production equipment (lathes, mills, etc.) within the shopfloor boundaries, satisfying spatial and relational constraints. | L62: Positions (2D coordinates on X/Z plane) and arrangement of preset equipment (CNC lathes, milling machines, drilling machines, inspection tables) within a shopfloor and production line. The layout follows I-, L- or U-shaped patterns while satisfying building, area and channel boundary constraints and inter-equipment constraints (safety distance, interference, maintenance space). | N62: Resolved | P62: Triage | Q62: No discussion needed | R62: paraphrases of the same content; narrative field, no categorical impact
A63: D062 | B63: S3 – Hu et al. (2026) | C63: strategic_planning_scope | D63: strategic_planning_scope.theoretical_framework_cited Type: list[TheoreticalFrameworkType] Planning-domain framework(s) the paper uses to structure its planning scope. General methods (MCDM, game theory, V&V principles, prompting techniques) and frameworks only cited as background do not count; then code 'none'. Types: - VDI-5200: VDI 5200 factory planning guideline - SC-Planning-Matrix: Supply Chain Planning Matrix (Fleischmann, Meyr, Wagner) - Lanza-et-al-2019: Global production network design (Lanza et al., CIRP Annals 2019) - Wiendahl-Nyhuis: Wiendahl-Nyhuis factory planning framework - Melo-Nickel-Saldanha-da-Gama-2009: Strategic logistics/distribution network design framework (Melo, Nickel, Saldanha-da-Gama 2009) - other: Another planning-domain framework or reference model (e.g., Systematic Layout Planning) that structures the paper's planning scope (specify) - none: No planning-domain framework used to structure the scope | E63: categorical | F63: High | G63: Only R1: none | Only R2: other | H63: none | I63: other | J63: [theoretical_framework_cited_reasoning] Muther's Systematic Layout Planning (SLP) is mentioned only as background in the Introduction ('the most classic approach is Richard Muther's Systematic Layout Planning'). It is not used to structure the method. CoT, ReAct and RAG are prompting techniques and do not count. [theoretical_framework_rationale] The method is structured around prompt engineering (task decomposition into Role/Space/Factory/Request, equipment models, and a think-generate-evaluate iteration) rather than any planning-domain framework. SLP and VDI 5200 are not used to structure the scope. | K63: [theoretical_framework_cited_reasoning] The paper cites 'Systematic Layout Planning (SLP)' by Richard Muther as the 'most classic approach' in Section 1. While SLP is a methodology/framework for layout planning, it is not one of the specific strategic planning frameworks listed in the enum (VDI-5200, SC-Planning-Matrix, etc.). Therefore, 'other' is the appropriate category, specifying SLP. | L63: none | N63: Resolved | O63: reasoning r1, no ther relevant framework used | Q63: Resolved by reviewers
A64: D063 | B64: S3 – Hu et al. (2026) | C64: strategic_planning_scope | D64: strategic_planning_scope.other_theoretical_framework_specification Type: str | None Free-text name and citation of the specific framework(s) utilized, not restricted to a controlled vocabulary. Required if 'other' was selected, otherwise null. | E64: free-text | F64: Medium | G64: Filled only by R2 | I64: Systematic Layout Planning (SLP) by Richard Muther | L64: NA | N64: Resolved | P64: Triage | Q64: Moot – follows resolved field | R64: parent value removed/none → field structurally inapplicable (D062)
A65: D064 | B65: S3 – Hu et al. (2026) | C65: llm_intervention | D65: llm_intervention.intervention_description Type: str Free-text description of the role the LLM/agent system plays in the planning task: inputs, outputs, and decision support function as reported. | E65: free-text | F65: Medium | G65: Text differs (similarity 8%) | H65: The LLM generates 2D shopfloor equipment layouts from structured prompts. The prompt template has three parts. (1) A task description, Task = {Role, Space, Factory, Request}, covering role prompt, coordinate-system space definition, factory boundaries, and layout requirements such as I/L/U-shaped patterns. (2) Output prompts, consisting of layout examples and JSON output structure hints. (3) Contextual knowledge units: equipment mathematical, text-information and constraint models, retrieved by Word2vec/cosine-similarity RAG. The LLM works in an iterative 'think-generate-evaluate' loop. In the thinking step it checks whether the information is sufficient and identifies missing knowledge, which triggers re-retrieval. In the generation step it outputs a JSON layout with equipment positions and rotations. In the evaluation step it is combined with human decision-making to check layout pattern and constraint compliance and to queue adjustment tasks. A parser then converts the JSON into a 3D scene using THREEJS and GLTF models. The method is validated on a small discrete manufacturing shopfloor (CNC lathes, mills, drills, inspection tables) for I-, L- and U-shaped layouts, compared against a CoT baseline. Separately, a spatial-reasoning Q&A dataset was used to test several LLMs. | I65: The LLM is used to generate shopfloor layout schemes by interpreting structured task descriptions (role, space, factory, requirements) and equipment knowledge. It performs spatial reasoning to determine the 2D coordinates and arrangement of rectangular equipment elements within a defined boundary, adhering to comprehensive and relational constraints. The system uses an iterative 'think-generate-evaluate' cycle to refine the layout, with the LLM acting as the core reasoning engine for spatial configuration and constraint satisfaction. | L65: The LLM generates 2D shopfloor equipment layouts from structured prompts. The prompt template has three parts. (1) A task description, Task = {Role, Space, Factory, Request}, covering role prompt, coordinate-system space definition, factory boundaries, and layout requirements such as I/L/U-shaped patterns. (2) Output prompts, consisting of layout examples and JSON output structure hints. (3) Contextual knowledge units: equipment mathematical, text-information and constraint models, retrieved by Word2vec/cosine-similarity RAG. The LLM works in an iterative 'think-generate-evaluate' loop. In the thinking step it checks whether the information is sufficient and identifies missing knowledge, which triggers re-retrieval. In the generation step it outputs a JSON layout with equipment positions and rotations. In the evaluation step it is combined with human decision-making to check layout pattern and constraint compliance and to queue adjustment tasks. A parser then converts the JSON into a 3D scene using THREEJS and GLTF models. The method is validated on a small discrete manufacturing shopfloor (CNC lathes, mills, drills, inspection tables) for I-, L- and U-shaped layouts, compared against a CoT baseline. Separately, a spatial-reasoning Q&A dataset was used to test several LLMs. | N65: Resolved | P65: Triage | Q65: No discussion needed | R65: paraphrases of the same content; narrative field, no categorical impact
A66: D065 | B66: S3 – Hu et al. (2026) | C66: llm_intervention | D66: llm_intervention.models Type: list[str] Exact name(s) + version (e.g., 'GPT-4o', 'Llama 3.1 70B') of only those LLMs deployed and evaluated with the paper's own method. If the version is not given, write e.g. 'ChatGPT (unspecified version)'. Do not list models that are merely discussed, cited or used outside the method (e.g., related work, external baselines); record those in models_rationale. | E66: multi-select | F66: High | G66: Only R2: ChatGLM3-6B; GPT-3.5 (turbo); GPT-4 | H66: Mixtral 8x7B | I66: Mixtral 8x7B; GPT-4; GPT-3.5 (turbo); ChatGLM3-6B | J66: Section 4.2 states that the open-source Mixtral 8x7B was deployed locally (temperature 0.5) for the method validation; the comparative experiments and ablation also all used Mixtral 8x7B. Section 4.1 tested GPT-3.5 (turbo), GPT-4, ChatGLM3-6B (14 March 2024 version) and Mixtral 8x7B on the authors' spatial-reasoning Q&A dataset. That test was a capability evaluation of LLMs, not a run of the full layout-generation method, so these models are not listed. This is borderline (?). ChatGPT is also mentioned in the introduction. | K66: Section 4.1 states: 'This paper tested several representative language models... GPT-3.5 (turbo) and GPT-4... ChatGLM3-6B and Mixtral 8x7B'. Section 4.2 states: 'In this case, this paper employed the open-source large language model Mixtral 8x7B for local deployment'. The Q&A dataset evaluation in 4.1 tests all four. The method validation in 4.2 specifically uses Mixtral 8x7B. GPT-4 and GPT-3.5 are used for the capability evaluation (Q&A dataset) and potentially as baselines or comparisons, but Mixtral is the primary model for the case study layout generation. The prompt says 'deployed and evaluated with the paper's own method'. The Q&A dataset is part of the evaluation of the LLMs' potential for the method. The case study uses Mixtral. I will include all tested models as they are evaluated in the context of the paper's proposed approach (spatial reasoning for layout). | L66: Mixtral 8x7B | N66: Resolved | O66: models mentioned from r2 extra are not deployed or validated just used in earlier test stages | Q66: Resolved by reviewers
A67: D066 | B67: S3 – Hu et al. (2026) | C67: llm_intervention | D67: llm_intervention.model_usage_context Type: str | None Free-text elaboration of which model is used for what, when multiple models are reported. | E67: free-text | F67: Medium | G67: Filled only by R1 | H67: Mixtral 8x7B is used for layout generation in the case study, the CoT-baseline comparison and the ablation. GPT-4, GPT-3.5, ChatGLM3-6B and Mixtral were benchmarked only on the spatial-reasoning Q&A dataset (Section 4.1, Figure 11). | L67: Mixtral 8x7B is used for layout generation in the case study, the CoT-baseline comparison and the ablation. GPT-4, GPT-3.5, ChatGLM3-6B and Mixtral were benchmarked only on the spatial-reasoning Q&A dataset (Section 4.1, Figure 11). | N67: Resolved | P67: Triage | Q67: Moot – follows resolved field | R67: models = Mixtral 8x7B only; R1 context explains the test-stage models (D065)
A68: D067 | B68: S3 – Hu et al. (2026) | C68: llm_intervention | D68: llm_intervention.model_family Type: list[ModelFamilyType] Model family classification(s) of the models listed in 'models'; non-empty iff models is non-empty. Types: - GPT: OpenAI GPT family (incl. o-series and ChatGPT) - Claude: Anthropic Claude family - Gemini: Google Gemini family (proprietary) - Gemma: Google Gemma family (open-weight) - Llama: Meta Llama family - Mistral: Mistral AI family, incl. Mixtral and other Mistral-derived models - Qwen: Alibaba Qwen family - DeepSeek: DeepSeek family - Phi: Microsoft Phi family - GLM: Zhipu AI / THUDM GLM family, incl. ChatGLM - ERNIE: Baidu ERNIE family - Command: Cohere Command family - Falcon: TII Falcon family - other: Other model family (specify) | E68: multi-select | F68: High | G68: Only R2: GLM; GPT | H68: Mistral | I68: Mistral; GPT; GLM | J68: Mixtral 8x7B is a Mistral AI sparse mixture-of-experts model (Section 4.1/4.2). | K68: Mixtral 8x7B is a Mistral-derived model (Section 4.1). GPT-4 and GPT-3.5 are OpenAI GPT family (Section 4.1). ChatGLM3-6B is the GLM family (Section 4.1). | L68: Mistral | N68: Resolved | O68: see llm intervention models | Q68: Resolved by reviewers
A69: D068 | B69: S3 – Hu et al. (2026) | C69: llm_intervention | D69: llm_intervention.open_weight Type: OpenWeightType Whether the weights of the models listed in 'models' are openly available. Types: - Y: Open-weight model (Llama, Mistral, Qwen, DeepSeek, ...) - N: Proprietary model (GPT, Claude, Gemini, ...) - mixed: System uses both open-weight and proprietary models - NR: Not reported: model not named precisely enough to decide (B9) | E69: categorical | F69: High | G69: Only R1: Y | Only R2: mixed | H69: Y | I69: mixed | J69: The paper calls Mixtral 8x7B 'open-source' and a SMoE model 'with open weights' (Sections 4.1, 4.2). | K69: Mixtral 8x7B is described as an 'open-source large language model' (Section 4.2) and 'open weights' (Section 4.1). ChatGLM3-6B is typically open-weight (Zhipu AI). GPT-4 and GPT-3.5 are proprietary (OpenAI). Thus, the set of models includes both open-weight and proprietary models. | L69: Y | N69: Resolved | O69: see llm intervention models | Q69: Resolved by reviewers
A70: D069 | B70: S3 – Hu et al. (2026) | C70: llm_intervention | D70: llm_intervention.model_size Type: str Parameter count(s) as reported (e.g., '70B', '8B; 70B'). NR if not reported (B9). | E70: free-text | F70: Medium | G70: Text differs (similarity 67%) | H70: 8x7B | I70: 8x7B; 6B | L70: 8x7B | N70: Resolved | P70: Triage | Q70: Moot – follows resolved field | R70: models = Mixtral 8x7B only → model size 8x7B (D065)
A71: D070 | B71: S3 – Hu et al. (2026) | C71: llm_intervention | D71: llm_intervention.deployment Type: DeploymentType Where the model(s) run. Types: - API: Hosted model accessed via a provider API or chat interface - local-on-prem: Model runs locally or on the organisation's own (on-prem/private-cloud) infrastructure - mixed: Both API and local models used - NR: Not reported | E71: categorical | F71: High | G71: Only R1: local-on-prem | Only R2: mixed | H71: local-on-prem | I71: mixed | J71: Section 4.2: 'employed the open-source large language model Mixtral 8 × 7B for local deployment'. | K71: Section 4.2 states Mixtral 8x7B was used for 'local deployment'. Section 4.1 mentions testing GPT-3.5 and GPT-4, which are typically accessed via API. The paper does not explicitly state how GPT models were accessed, but 'local deployment' is explicitly stated for Mixtral. Given the mix of open-source (local) and proprietary (likely API) models, 'mixed' is the most accurate classification. | L71: local-on-prem | N71: Resolved | O71: see llm intervention models | Q71: Resolved by reviewers
A72: D071 | B72: S3 – Hu et al. (2026) | C72: llm_intervention | D72: llm_intervention.prompting_techniques Type: list[PromptingTechnique] Prompting technique(s) used by the paper's method, pick all applicable; 'NR' (exclusive) if prompting is not described. Types: - zero-shot: Instructions only, no worked examples - few-shot: In-context examples of input/output pairs - CoT: Model is asked for intermediate reasoning steps - self-consistency: Several sampled outputs aggregated (e.g., majority vote) - ReAct: Interleaved reasoning and tool actions - structured-output: Output constrained to a schema or grammar (JSON schema, function calling) - other: Other technique (e.g., tree-of-thoughts, role prompting) (specify) - NR: Prompting not described | E72: multi-select | F72: High | G72: Only R1: ReAct; few-shot | H72: few-shot; CoT; ReAct; structured-output; other | I72: CoT; structured-output; other | J72: Section 3.2.3: the output prompt includes 'examples of layouts and output structure hints' (few-shot, structured JSON output). Section 3.2.1: role prompts define the LLM's role (role prompting, coded as other). Section 3.3: a stepwise think-generate-evaluate reasoning chain 'inspired by advanced frameworks such as COT and ReAct'. In it, the thinking step identifies missing knowledge and triggers retrieval (Figure 9, 'Action: Retrieve relevant information'), which is a ReAct-like interleaving of reasoning and action. Task decomposition into subtasks and keyword strategies are also described. | K72: Section 3.3 mentions 'a stepwise strategy inspired by advanced frameworks such as COT (Chain-of-Thought)'. The method uses an iterative 'think-generate-evaluate' cycle which aligns with CoT/ReAct-like reasoning. Section 3.2.3 describes constructing prompt templates with 'output structure hints' and using JSON, which fits 'structured-output'. The 'other' category is used for the specific 'Prompt Engineering' strategies described, such as role prompting, space definition, and knowledge unit integration, which are specific to this domain application. | L72: few-shot; CoT; ReAct; structured-output; other | N72: Resolved | O72: see reasoning r1 | Q72: Resolved by reviewers
A73: D072 | B73: S3 – Hu et al. (2026) | C73: llm_intervention | D73: llm_intervention.other_prompting_technique_specification Type: str | None Free-text specification of the prompting technique. Required if 'other' was selected, otherwise null. | E73: free-text | F73: Medium | G73: Text differs (similarity 43%) | H73: Role prompting; task decomposition into subtasks; dynamic/static prompt templates with retrieved knowledge units. | I73: Role prompting, Space definition, Factory description, Layout requirements, Knowledge unit integration (RAG-based), Iterative think-generate-evaluate loop. | L73: Role prompting; task decomposition into subtasks; dynamic/static prompt templates with retrieved knowledge units. | N73: Resolved | P73: Triage | Q73: Moot – follows resolved field | R73: 'other' kept; R1 names techniques, R2 lists prompt-template components (D071)
A74: D073 | B74: S3 – Hu et al. (2026) | C74: llm_intervention | D74: llm_intervention.workflow_patterns Type: list[WorkflowPattern] All workflow patterns used inside the method, at any level of nesting; 'none' is exclusive. Types: - prompt-chaining: Fixed sequence of LLM calls, each processing the previous output - routing: An LLM call classifies the input and sends it to a specialised follow-up - parallelization: Independent LLM calls run in parallel (sectioning or voting) and are aggregated - orchestrator-workers: A central LLM breaks the task down at run time and delegates to workers - evaluator-optimizer: One LLM generates, another evaluates and feeds back, in a loop - none: None of these patterns (single call or single autonomous agent) | E74: multi-select | F74: High | G74: Only R1: prompt-chaining | H74: prompt-chaining; evaluator-optimizer | I74: evaluator-optimizer | J74: The think, generate and evaluate steps are 'connected in series to form a reasoning chain' (prompt-chaining). The evaluation step (LLM assessment plus human decision) identifies adjustments and adds tasks to the queue for regeneration, iterating until tasks are exhausted (evaluator-optimizer; Section 3.3, Figure 9). | K74: Section 3.3 describes an 'iterative reasoning mechanism' with 'thinking, generation, and evaluation' connected in series. The evaluation step assesses the generated layout and feeds back adjustments for the next iteration. This matches the 'evaluator-optimizer' pattern where one component generates and another (or the same in a loop) evaluates and refines. | L74: prompt-chaining; evaluator-optimizer | N74: Resolved | O74: see reasoning r1 | Q74: Resolved by reviewers
A75: D074 | B75: S3 – Hu et al. (2026) | C75: llm_intervention | D75: llm_intervention.tool_use Type: bool True if an LLM component itself decides to call tools/functions at run time (Schick et al., 'Toolformer', NeurIPS 2023); developer-fixed calls to external components are coded only in integrations. | E75: boolean | F75: High | G75: R1 TRUE vs R2 FALSE | H75: TRUE | I75: FALSE | J75: Memory: a task queue and iteration state are kept within one layout session; there is no persistent cross-task memory. Planning/reflection: the thinking step assesses whether information is sufficient, and the evaluation step has the LLM assess whether the generated layout meets the pattern and constraints and pinpoint issues (Figure 9). Tool use: in the thinking step the LLM identifies the missing knowledge, and the system then 're-initiates the information retrieval process' (Section 3.3; Figure 9 'Action: Retrieve relevant information'). This is an LLM-driven decision to retrieve, coded true with some uncertainty (?), since the retrieval itself may be system-executed. | K75: Agent Memory: The system maintains context within the iterative loop (short-term) to refine the layout based on previous evaluations. It does not mention persistent long-term memory across different tasks. Planning/Reflection: The 'Thinking' stage explicitly assesses information completeness and plans the next step, and the 'Evaluation' stage reflects on the generated output to identify issues. Tool Use: The LLM does not dynamically decide to call external tools at runtime; the RAG retrieval is a fixed step in the pipeline triggered by the workflow, not a tool call decided by the LLM agent in the sense of Toolformer/ReAct where the LLM outputs a tool call instruction. The RAG is part of the fixed pipeline architecture. | L75: TRUE | N75: Resolved | O75: tool calling is not explizitly mentioned but principles of tool calling used see figure 9 | Q75: Resolved by reviewers
A76: D075 | B76: S3 – Hu et al. (2026) | C76: or_substrate | D76: or_substrate.optimization_tradition_present Type: bool True only if the proposed method itself formulates or solves an optimization/OR problem (e.g., a MILP, a metaheuristic or RL search, an MCDM ranking, a solver call, or an LLM-generated model that is then solved). False if optimization appears only in the introduction, related work, or background, or only as a baseline the method is compared against; note such mentions in the reasoning. | E76: boolean | F76: High | G76: R1 TRUE vs R2 FALSE | H76: TRUE | I76: FALSE | J76: Borderline case (?). The proposed method has no mathematical program, no solver and no metaheuristic. Instead, an LLM (Mixtral 8x7B) generates shopfloor layouts, i.e., coordinates of rectangular equipment in 2D. It does this inside an iterative 'think-generate-evaluate' loop (Sec. 3.3). Each round's layout is checked against constraints (safety distances, boundaries, overlap/interference) and layout-pattern requirements, and the next round refines it. The task is framed as a facility layout problem: 'determine the positioning and arrangement of these elements… to meet design conditions and achieve specific design objectives' (Sec. 3.2.1). Results are scored on space utilization and constraint satisfaction (Sec. 4.2, Table 2). This amounts to an LLM-driven iterative search over a constrained layout problem, so it is coded as present. However, the authors explicitly distance the work from optimization: 'generative methods are not directly comparable to traditional approaches' (Sec. 4.2). Classical optimization (SLP-based GA, PSO, SA, RL) appears only in the Introduction and Related Work. | K76: The paper proposes a method based on Large Language Models (LLMs) and Prompt Engineering to generate shopfloor layouts. It explicitly states in Section 4.2 that 'In traditional workshop layout methods, the layout is developed using mathematical models and optimization algorithms... In contrast, language models are data-driven and generative'. The proposed method does not formulate or solve a formal optimization problem (like MILP, metaheuristic, or RL) itself; instead, it uses LLM reasoning (Chain-of-Thought, ReAct-style iteration) to generate solutions. Optimization algorithms are only mentioned in the Introduction and Related Works as background or traditional approaches, not as part of the proposed method's core mechanism. | L76: FALSE | N76: Resolved | O76: see reasoning r2 | Q76: Resolved by reviewers
A77: D076 | B77: S3 – Hu et al. (2026) | C77: or_substrate | D77: or_substrate.formalization_level Type: FormalizationLevel Formalization level of the optimization the proposed method itself performs; 'none' iff optimization_tradition_present is false. Types: - high: Explicit mathematical program (variables, objective, constraints) solved exactly or to a bound - medium: Explicit objective and constraints, solved by approximate search or scoring (metaheuristic, RL, simulation-optimization, MCDM) - low: Objective/criteria named informally; no formal model - none: No optimization tradition present | E77: categorical | F77: High | G77: Only R1: low | Only R2: none | H77: low | I77: none | J77: No explicit objective function or formal model is stated. Constraints are described in structured JSON/text form (comprehensive and relationship constraints, Sec. 3.2.2, Fig. 6). Objectives such as space utilization and layout-pattern conformity are named informally and are evaluated by the LLM plus human decision-making (Fig. 9). Hence the level is low. | K77: Since the proposed method does not perform formal optimization (optimization_tradition_present is false), the formalization level is 'none'. The method relies on semantic representation and prompt engineering rather than mathematical programming. | L77: none | N77: Resolved | O77: see optimization method present | Q77: Resolved by reviewers
A78: D077 | B78: S3 – Hu et al. (2026) | C78: or_substrate | D78: or_substrate.optimization_paradigm Type: list[OptimizationParadigm] All optimization paradigms the method itself uses; non-empty iff optimization_tradition_present is true. Types: - MILP-LP: Linear or mixed-integer linear program - NLP: Nonlinear (incl. MINLP, quadratic) program - CP: Constraint programming / SAT - stochastic-robust: Stochastic, robust or chance-constrained program - metaheuristic: Metaheuristic or constructive heuristic (GA, SA, tabu, ...) - RL: Reinforcement learning - MCDM: Multi-criteria decision making (AHP, TOPSIS, PROMETHEE, ...) - simulation-optimization: Optimization over a simulation model - other: Other paradigm (specify) | E78: multi-select | F78: High | G78: Only R1: other | H78: other | J78: The search is performed by prompting an LLM iteratively: CoT/ReAct-inspired think-generate-evaluate cycles with RAG retrieval of equipment knowledge (Word2vec + cosine similarity). None of the listed paradigms (MILP, metaheuristic, RL, etc.) applies. | K78: No optimization paradigm is used by the proposed method. The method uses LLM generation and iterative reasoning (Think-Generate-Evaluate), which is not classified as a standard OR optimization paradigm in this schema. Traditional paradigms like metaheuristics or RL are mentioned only as related work or baselines, not as the method's own optimization engine. | N78: Resolved | O78: see optimization method present | Q78: Resolved by reviewers
A79: D078 | B79: S3 – Hu et al. (2026) | C79: or_substrate | D79: or_substrate.other_optimization_paradigm_specification Type: str | None Free-text specification of the paradigm. Required if 'other' was selected, otherwise null. | E79: free-text | F79: Medium | G79: Filled only by R1 | H79: LLM-based generative iterative refinement (prompt-engineered think-generate-evaluate loop with RAG and human/LLM evaluation) for constrained 2D facility layout | L79: NA | N79: Resolved | P79: Triage | Q79: Moot – follows resolved field | R79: parent value removed/none → field structurally inapplicable (D077)
A80: D079 | B80: S3 – Hu et al. (2026) | C80: or_substrate | D80: or_substrate.llm_or_role Type: list[LLMORRole] All roles the LLM plays relative to the optimizer, pick all applicable; 'none' (exclusive) if there is no optimizer or the LLM does not interact with it. Types: - formulator: Translates natural language into an optimization model or solver code - direct-optimizer: LLM itself proposes and iteratively improves solutions (OPRO-style) - heuristic-designer: LLM designs or evolves algorithms/heuristics that are then run - solver-orchestrator: LLM calls a solver as a tool and handles inputs/outputs - result-interpreter: LLM explains solutions or answers what-if questions on them (OptiGuide-style) - verifier: LLM checks models or solutions for errors, feasibility or plausibility - none: No optimizer in the method, or the LLM does not interact with it | E80: multi-select | F80: High | G80: Only R1: verifier | H80: direct-optimizer; verifier | I80: direct-optimizer | J80: The LLM itself proposes layout solutions as JSON coordinates and refines them over iterations based on evaluation feedback (Sec. 3.3, Fig. 9), which fits 'direct-optimizer' (?). In the evaluation stage, 'LLMs Assessment' combined with human decision-making checks whether outcomes align with the layout pattern and which constraints are not fulfilled (Fig. 9), which fits 'verifier'. No external solver is used. | K80: The LLM acts as the primary engine for generating and refining the layout solution. Section 3.3 describes a 'Multi-step reasoning iteration' where the LLM performs 'thinking, generation, and evaluation' to iteratively improve the layout. This aligns with the 'direct-optimizer' role where the LLM itself proposes and iteratively improves solutions, rather than just formulating a model for an external solver or designing a heuristic algorithm to be run separately. It does not call an external solver (solver-orchestrator) nor does it primarily verify existing solutions (verifier) in the context of an external optimizer. | L80: none | N80: Resolved | O80: see reasoning r1 | P80: Triage | Q80: Moot – follows resolved field | R80: Option A (decided in chat): no optimizer in the method (D075 = FALSE) → none; iterative refinement documented under workflow_patterns (evaluator-optimizer)
A81: D080 | B81: S3 – Hu et al. (2026) | C81: or_substrate | D81: or_substrate.optimization_description Type: str | None Free-text description of what is formulated and optimized as reported: decision variables, objective function, constraints. | E81: free-text | F81: Medium | G81: Filled only by R1 | H81: Decision variables: 2D positions (x, z) of rectangular equipment with known length and width, kept parallel to the shopfloor boundaries. Constraints: comprehensive constraints (building, area and channel boundaries; safety distance to structures) and relationship constraints (inter-equipment safety gaps, maintenance space, no overlap or interference), plus a required layout pattern (I-, L- or U-shaped). Objectives/evaluation criteria (informal): completeness/compliance, space utilization, layout-requirement satisfaction and constraint satisfaction. These are pursued through iterative LLM generation and evaluation rather than a formal objective function. | L81: NA | N81: Resolved | P81: Triage | Q81: Moot – follows resolved field | R81: parent value removed/none → field structurally inapplicable (D075)
A82: D081 | B82: S3 – Hu et al. (2026) | C82: evaluation_and_outcomes | D82: evaluation_and_outcomes.dataset_or_benchmark Type: str Dataset or benchmark name and size as reported. NR if absent. | E82: free-text | F82: Medium | G82: Text differs (similarity 78%) | H82: Author-built spatial-reasoning Q&A dataset (340 questions; categories: absolute/relative position 57, coordinate transformation 85, spatial relationship 107, circumstances 91); not public | I82: Author-constructed Q&A dataset (340 questions: 57 absolute/relative position, 85 coordinate transformation, 107 spatial relationship, 91 circumstances) | J82: Table 1 and Sec. 4.1 describe the dataset. It was derived from multi-source enterprise documents (motor manufacturing, machining workshops, textile companies), rewritten and augmented, then expert-reviewed. It cannot be made public because it contains proprietary enterprise information. | K82: Section 4.1 and Table 1 describe a specialized Q&A dataset constructed by the authors to evaluate LLMs' spatial reasoning. The total number of questions is the sum of the counts in Table 1 (57+85+107+91 = 340). The dataset is not public due to proprietary enterprise information. | L82: Author-built spatial-reasoning Q&A dataset (340 questions; categories: absolute/relative position 57, coordinate transformation 85, spatial relationship 107, circumstances 91); not public | N82: Resolved | P82: Triage | Q82: No discussion needed | R82: same dataset and size; R1 adds availability/source detail
A83: D082 | B83: S3 – Hu et al. (2026) | C83: record | D83: n_reported_metrics Number of reported metrics (one row each on the reported_metrics sheet). | E83: categorical | F83: High | G83: Only R1: 15 | Only R2: 9 | H83: 15 | I83: 9 | J83: The Fig. 11 accuracy values are not stated numerically in the text and were read approximately from the bar chart, so they are uncertain ('?'). The Table 2 and Table 3 values are reported exactly. The Table 2 element counts are 8, 10 and 15. | K83: Metrics are extracted from Table 2 (Comparison of COT with proposed method) and Table 3 (Ablation study) in Section 4.2. The values are normalized scores (0-1) for space utilization, compliance, layout pattern accuracy, and constraint satisfaction. The Q&A dataset accuracy is shown in Figure 11 but specific numerical values per model/category are not explicitly tabulated in text, only described qualitatively as 'high accuracy' and 'GPT-4 significantly outperformed'. | L83: 15 | N83: Resolved | O83: see reasoning r1 | Q83: Resolved by reviewers
A84: D083 | B84: S3 – Hu et al. (2026) | C84: evaluation_and_outcomes | D84: evaluation_and_outcomes.sample_size Type: str Number of test cases, users, or records as reported. NR if absent. | E84: free-text | F84: Medium | G84: Text differs (similarity 51%) | H84: 340 Q&A questions; case layouts with 8, 10 and 15 elements; ablation with 10 devices | I84: 340 Q&A items; 1 case study with 3 layout patterns (I, L, U) and varying element counts (8, 10, 15) | J84: The question count is summed from Table 1 (57+85+107+91=340). Element counts come from Table 2, and the ablation configuration from Sec. 4.2. | K84: Table 1 lists the number of questions per category (57+85+107+91=340). Section 4.2 describes the case study using a single shopfloor scenario with 3 layout patterns and testing with 8, 10, and 15 equipment elements. | L84: 340 Q&A questions; case layouts with 8, 10 and 15 elements; ablation with 10 devices | N84: Resolved | P84: Triage | Q84: No discussion needed | R84: R1 contains all R2 counts (superset)
A85: D084 | B85: S3 – Hu et al. (2026) | C85: evaluation_and_outcomes | D85: evaluation_and_outcomes.reported_limitations Type: list[str] 1-3 sentence paraphrase of author-stated limitations. Empty list if none are stated (= NR). | E85: free-text | F85: Medium | G85: Text differs (similarity 15%) | H85: The method requires detailed equipment information, clearly known equipment constraints, and expert involvement during generation.; Layout reasoning becomes harder when device constraints are unknown or must be mined deeply, or when hard and soft constraints must be fully satisfied in complex scenarios, because the method relies on general LLM capability without downstream task adaptation or fine-tuning.; The problem is simplified to a 2D plane with rectangular equipment; the Q&A dataset is small-scale and cannot be made public; and generative methods are not directly comparable to traditional optimization approaches. | I85: The method relies on sufficient support from detailed equipment information and clear knowledge of equipment constraints.; Layout reasoning is challenging when device constraints are unknown or need to be mined deeply.; The method mainly utilizes the generalized capability of the LLM without deeper downstream task adaptation training (fine-tuning). | J85: Drawn from Sec. 5 (Discussion), Sec. 3.2.1 (2D simplification), Sec. 4.1 (dataset not public, small-scale) and Sec. 4.2 (non-comparability with traditional methods). | K85: Section 5 (Discussion) explicitly states these limitations: 'It is important to note that the proposed method is suitable when there is sufficient support from detailed equipment information... layout reasoning will be more challenging when the constraints of the device are unknown... This is due to the fact that the method in this paper mainly utilizes the generalized capability of the large language model without deeper downstream task adaptation training.' | L85: The method requires detailed equipment information, clearly known equipment constraints, and expert involvement during generation.; Layout reasoning becomes harder when device constraints are unknown or must be mined deeply, or when hard and soft constraints must be fully satisfied in complex scenarios, because the method relies on general LLM capability without downstream task adaptation or fine-tuning.; The problem is simplified to a 2D plane with rectangular equipment; the Q&A dataset is small-scale and cannot be made public; and generative methods are not directly comparable to traditional optimization approaches.; The method relies on sufficient support from detailed equipment information and clear knowledge of equipment constraints.; Layout reasoning is challenging when device constraints are unknown or need to be mined deeply.; The method mainly utilizes the generalized capability of the LLM without deeper downstream task adaptation training (fine-tuning). | N85: Resolved | P85: Triage | Q85: No discussion needed | R85: different limitation items → union kept for Tier-3 thematic coding
A86: D085 | B86: S3 – Hu et al. (2026) | C86: evaluation_and_outcomes | D86: evaluation_and_outcomes.outcome_summary Type: str | None Free-text narrative summary of the main results beyond isolated metrics, as reported. | E86: free-text | F86: Medium | G86: Text differs (similarity 1%) | H86: All four LLMs showed reasonably high accuracy on the spatial-reasoning Q&A set, with GPT-4 best and Mixtral 8x7B performing surprisingly well. In the shopfloor case using Mixtral 8x7B, the proposed prompt-engineering method (structured JSON representation, RAG-based knowledge units, think-generate-evaluate iteration) outperformed a CoT baseline on space utilization, I/L/U layout pattern accuracy, and constraint satisfaction, especially as element count increased. Compliance was similar for both. Ablation showed that removing constraint representation sharply reduced constraint satisfaction (0.013), and that removing question decomposition or multi-step iteration also degraded results. | I86: The proposed method significantly outperforms the Chain-of-Thought (CoT) baseline in space utilization, layout pattern accuracy, and constraint satisfaction across different numbers of equipment elements. Ablation studies confirm that Question Decomposition, Constraint Representation, and Multi-step Iteration modules all contribute positively to the final layout quality, with Constraint Representation having a particularly strong impact on avoiding overlaps and conflicts. | L86: All four LLMs showed reasonably high accuracy on the spatial-reasoning Q&A set, with GPT-4 best and Mixtral 8x7B performing surprisingly well. In the shopfloor case using Mixtral 8x7B, the proposed prompt-engineering method (structured JSON representation, RAG-based knowledge units, think-generate-evaluate iteration) outperformed a CoT baseline on space utilization, I/L/U layout pattern accuracy, and constraint satisfaction, especially as element count increased. Compliance was similar for both. Ablation showed that removing constraint representation sharply reduced constraint satisfaction (0.013), and that removing question decomposition or multi-step iteration also degraded results. | N86: Resolved | P86: Triage | Q86: No discussion needed | R86: paraphrases of the same content; narrative field, no categorical impact
A87: D086 | B87: S3 – Hu et al. (2026) | C87: gap_indicators | D87: gap_indicators.hitl_type Type: Annotated[list[HITLType], AfterValidator(func=<function <lambda> at 0x7ff41b44c670>)] | None All HITL patterns present, required if hitl_pattern_present is true. Classify by who triggers the human step (workflow, human, system) and when. Types: - approval-gate: Workflow-initiated: a human must check and accept or repair output before the workflow proceeds - what-if-interface: Human-initiated: human poses scenarios or changes inputs to explore outcomes - escalation-protocol: System-initiated: the system detects uncertainty, failure or missing information and asks the human - iterative-feedback: Human judges each iteration's output and gives guidance that steers the next iteration - human-override: Human edits or vetoes the agents' intermediate decisions or plans - other: Other HITL pattern (specify) | E87: multi-select | F87: High | G87: Only R2: approval-gate | H87: iterative-feedback | I87: iterative-feedback; approval-gate | J87: Section 3.3 and Figure 9: each iteration ends in an evaluation where a human ('Decision-making') and the LLM assess the generated layout and give "guidance for necessary adjustments". This identifies tasks to add to the queue for the next cycle, which steers the next iteration. In the COT baseline (Sec 4.2), experts also "continue to give appropriate layout knowledge and prompts for guidance", but that applies to the baseline, not the proposed method. | K87: The system uses an iterative loop where the human evaluates the generated layout and provides guidance for the next iteration ('iterative-feedback'). The evaluation step acts as a gate where the human decides if the layout is acceptable or needs adjustment ('approval-gate'). Section 3.3: 'The evaluation part is to evaluate the LLMs of the generated layout and make manual decisions... and guidance for necessary adjustments.' | L87: iterative-feedback | N87: Resolved | O87: for “approval-gate” human actively needs to adapt output manually if something is wrong | Q87: Fix consensus (format/schema) | R87: lower-case vocabulary term → proposed: iterative-feedback
A88: D087 | B88: S3 – Hu et al. (2026) | C88: gap_indicators | D88: gap_indicators.hitl_description Type: str | None Free-text elaboration of how the HITL pattern operates in the system, as reported. | E88: free-text | F88: Medium | G88: Text differs (similarity 10%) | H88: In the think-generate-evaluate loop, the evaluation stage combines LLM self-assessment with manual human decision-making. Together they check the layout against the layout pattern, constraints and overall requirements, and give adjustment guidance that defines the tasks for the next iteration. | I88: The system employs a 'think-generate-evaluate' loop. In the evaluation phase, a human expert reviews the generated layout, checks for constraint violations or logical errors, and provides feedback or adjustments to guide the next iteration of the LLM's reasoning and generation process. | L88: In the think-generate-evaluate loop, the evaluation stage combines LLM self-assessment with manual human decision-making. Together they check the layout against the layout pattern, constraints and overall requirements, and give adjustment guidance that defines the tasks for the next iteration. | N88: Resolved | P88: Triage | Q88: Moot – follows resolved field | R88: description follows consensus hitl_type (= R1, no approval-gate) (D086)
A89: D088 | B89: S3 – Hu et al. (2026) | C89: gap_indicators | D89: gap_indicators.domain_knowledge_type Type: Annotated[list[DomainKnowledgeType], AfterValidator(func=<function <lambda> at 0x7ff41b44c670>)] | None All types of domain knowledge formalization present, required if domain_knowledge_formalization_present is true. Types: - ontology: Formal ontology: classes, relations and axioms of the domain (e.g., OWL), schema level - knowledge-graph: Knowledge graph: domain instances and their relations stored as a graph - standards-encoding: Machine-readable encoding of domain standards (e.g., VDI 5200, ISA-95, ISO 22400) - structured-schema: Non-graph metamodel or schema (e.g., JSON Schema, UML) for domain entities and constraints - relational-database: Relational database or taxonomy of domain entities and attributes - code-template: Code or model template encoding domain structure (e.g., simulation blueprint) - mathematical-model: Optimization or simulation model encoding domain structure and rules - other: Other domain knowledge formalization (specify) | E89: multi-select | F89: High | G89: Only R1: mathematical-model | H89: structured-schema; mathematical-model | I89: structured-schema | J89: Structured-schema: the UML metamodel and JSON format for shopfloor/production line/equipment, including constraint fields (Sec 3.1, Figs 1-2). Mathematical-model: the 'Mathematical Model: For accurately quantifying equipment dimensions and spatial requirements' and the 2D coordinate representation of rectangular elements (Sec 3.2.1-3.2.2, Fig 5). The knowledge units (E, R) resemble a graph, but no explicit knowledge graph is described, and retrieval uses Word2vec plus cosine similarity. Knowledge graph was therefore not coded (?). | K89: The paper defines an 'information metamodel' with three levels (Shopfloor, Production Line, Equipment) and specific attributes for each. It uses JSON as the data format. This fits the definition of a 'structured-schema' (non-graph metamodel or schema for domain entities and constraints). It is not a formal ontology (OWL/RDF) or a knowledge graph in the traditional sense, but a structured data schema. Section 3.1: 'An information metamodel is a framework for describing and representing information... Three levels were designed...'. | L89: structured-schema; mathematical-model | N89: Resolved | O89: see reasoning r1 | Q89: Resolved by reviewers
A90: D089 | B90: S3 – Hu et al. (2026) | C90: gap_indicators | D90: gap_indicators.domain_knowledge_description Type: str | None Free-text elaboration of what domain knowledge is formalized and how, as reported. | E90: free-text | F90: Medium | G90: Text differs (similarity 7%) | H90: A hierarchical information metamodel (Shopfloor > Production line > Equipment) is encoded in JSON (DTDL-like ids, GLTF model references). Equipment attributes cover basic info, geometric info (work area, interference range, dimensions), position/rotation and layout constraints (inter/intra: building, area and channel boundaries; relationship constraints with target, relation, type, value and rules). Each piece of equipment has a mathematical, a text information and a constraint model. Knowledge units of elements and relations are retrieved via Word2vec/cosine RAG into the prompt templates. A parser validates the generated JSON and drives THREE.js 3D rendering. | I90: The domain knowledge is formalized as a three-level information metamodel: Shopfloor Level (macro functional areas), Production Line Unit Level (process carriers), and Equipment Level (basic layout elements). Each level has defined attributes such as UUID, display name, position, dimensions, and constraints (comprehensive and relational). This structure is serialized in JSON format to be used as input for the LLM. | L90: A hierarchical information metamodel (Shopfloor > Production line > Equipment) is encoded in JSON (DTDL-like ids, GLTF model references). Equipment attributes cover basic info, geometric info (work area, interference range, dimensions), position/rotation and layout constraints (inter/intra: building, area and channel boundaries; relationship constraints with target, relation, type, value and rules). Each piece of equipment has a mathematical, a text information and a constraint model. Knowledge units of elements and relations are retrieved via Word2vec/cosine RAG into the prompt templates. A parser validates the generated JSON and drives THREE.js 3D rendering. | N90: Resolved | P90: Triage | Q90: Moot – follows resolved field | R90: description follows consensus type (= R1) (D088)
A91: D090 | B91: S3 – Hu et al. (2026) | C91: gap_indicators | D91: gap_indicators.evaluation_framework_type Type: Annotated[list[EvaluationFrameworkType], AfterValidator(func=<function <lambda> at 0x7ff41b44c670>)] | None All framework elements used, required if evaluation_framework_used is true. Code both the test instrument (benchmark, custom test set, expert ground truth) and the scoring (rubric, domain-specific metric). Types: - benchmark: Public, standardised benchmark reused from prior work - custom-test-set: Test items or cases built by the authors for this paper - expert-ground-truth: Outputs compared with expert or practitioner decisions - rubric: Graded scoring scale or criteria (incl. Likert ratings, ordinal suitability levels) - domain-specific-metric: Metric defined by the planning domain (e.g., throughput, space utilisation, cost); not generic accuracy/F1 - other: Other evaluation framework (specify) | E91: multi-select | F91: High | G91: Only R1: expert-ground-truth | H91: custom-test-set; expert-ground-truth; domain-specific-metric | I91: custom-test-set; domain-specific-metric | J91: Custom-test-set: the authors' Q&A dataset built from enterprise documents, and the case scenarios. Expert-ground-truth: Q&A answers were designed and matched by professional team members, with expert review ("professional team members to design questions and match answers based on domain knowledge"). Domain-specific-metric: space utilization and constraint satisfaction (comprehensive/relational) in Table 2. | K91: The authors created a 'specialized Q&A dataset' (Section 4.1) to test spatial reasoning, which is a custom test set. For the layout generation task, they use domain-specific metrics such as 'space utilization', 'compliance', and constraint satisfaction scores (Section 4.2, Table 2). | L91: custom-test-set; expert-ground-truth; domain-specific-metric | N91: Resolved | O91: see reasoning r1 | Q91: Resolved by reviewers
A92: D091 | B92: S3 – Hu et al. (2026) | C92: gap_indicators | D92: gap_indicators.evaluation_framework_description Type: str | None Free-text elaboration of the evaluation framework and its application, as reported. | E92: free-text | F92: Medium | G92: Text differs (similarity 7%) | H92: Two parts. (1) A spatial-reasoning Q&A benchmark covering absolute/relative position, coordinate transformation, spatial relationship and circumstances; accuracy is assessed per LLM. (2) Layout generation with Mixtral 8x7B (temperature 0.5) against a COT baseline (max 10 rounds) across element counts and layout shapes, using space utilization, compliance, layout requirement satisfaction and constraint satisfaction. An ablation of question decomposition, constraint representation and multi-step iteration used 10 devices in a U-shape with 6 iterations. | I92: The evaluation consists of two parts: 1) A custom Q&A dataset covering absolute/relative position, coordinate transformation, spatial relationships, and practical scenarios to test LLM spatial cognition. 2) A case study comparison using metrics like space utilization, compliance, and constraint adherence (comprehensive and relational) to assess the quality of generated layouts against a COT baseline. | L92: Two parts. (1) A spatial-reasoning Q&A benchmark covering absolute/relative position, coordinate transformation, spatial relationship and circumstances; accuracy is assessed per LLM. (2) Layout generation with Mixtral 8x7B (temperature 0.5) against a COT baseline (max 10 rounds) across element counts and layout shapes, using space utilization, compliance, layout requirement satisfaction and constraint satisfaction. An ablation of question decomposition, constraint representation and multi-step iteration used 10 devices in a U-shape with 6 iterations. | N92: Resolved | P92: Triage | Q92: Moot – follows resolved field | R92: description follows consensus type (= R1) (D090)
A93: D092 | B93: S3 – Hu et al. (2026) | C93: gap_indicators | D93: gap_indicators.automation_stage Type: list[AutomationStage] All information-processing stages the LLM system automates (Parasuraman et al. 2000). Types: - information-acquisition: Gathering and filtering input data/documents (intelligence) - information-analysis: Integrating, interpreting, predicting; generating alternatives (intelligence/design) - decision-selection: Evaluating and ranking alternatives, recommending or choosing one (choice) - action-implementation: Carrying out the decision (writing it into a plan/system, triggering actions) | E93: multi-select | F93: High | G93: Only R1: action-implementation; information-acquisition | Only R2: decision-selection | H93: information-acquisition; information-analysis; action-implementation | I93: information-analysis; decision-selection | J93: Information-acquisition: RAG retrieval of equipment knowledge, plus a thinking step that identifies missing knowledge and re-retrieves (Sec 3.3). Information-analysis: the LLM generates layout schemes (positions/rotations in JSON) and evaluates them against constraints. Action-implementation: the generated JSON is parsed and rendered into a 3D scene via THREE.js (Sec 3.1). This is borderline, since it writes the plan into a visualization system (?). Final decision selection rests with human decision-making. | K93: The system analyzes the input layout requirements and equipment data to generate a layout plan (information-analysis/design). It then selects a specific arrangement of equipment that satisfies constraints (decision-selection). It does not implement the physical layout (action-implementation) nor does it primarily focus on acquiring raw data from sensors (information-acquisition), though it retrieves knowledge from a database (RAG). The core contribution is the generation of the layout plan itself. | L93: information-acquisition; information-analysis | N93: Resolved | O93: Information-acquisition: RAG retrieval of equipment knowledge; not decision-selection because it does not actively ranks the alternatives | Q93: Fix consensus (format/schema) | R93: lower-case + "; " separator → proposed: information-acquisition; information-analysis
A94: D093 | B94: S3 – Hu et al. (2026) | C94: quality_appraisal | D94: quality_appraisal.q2_empirical_or_demonstration_grounding Type: AppraisalAnswer Q2, read by study-type category (derived from validation_status): A: are metrics defined and results reported with context (sample size, variance, comparator)? B: is the artifact demonstrated on a case that exercises its core claims? C: is the argumentation internally consistent and traceable? Types: - Yes: Criterion fully met - Partially: Criterion partly met - No: Criterion not met | E94: categorical | F94: High | G94: Only R1: Partially | Only R2: Yes | H94: Partially | I94: Yes | J94: I treat this as category A/B (empirical comparison on a case). Strengths: - A Q&A dataset (Table 1: 57/85/107/91 questions) was used to test four LLMs (Fig. 11). - The method was compared with a CoT baseline on Mixtral 8x7B across element counts 8/10/15 and I/L/U layouts (Table 2). - An ablation study is reported (Table 3). Weaknesses: - Metric definitions are only qualitative ('Space utilization measures the efficiency of space use…'); how scores such as layout-requirement accuracy are computed is unclear. - No variance, no repeated runs and no statistical tests are reported. - Sample sizes per Table 2 condition are not stated. - The CoT baseline relies on experts giving guidance, and the evaluation is partly manual. - Fig. 11 accuracies are shown only as bars. - The case is a single small shopfloor. | K94: The paper provides a Q&A dataset for spatial reasoning evaluation (Table 1, Figure 11) and a case study comparing the proposed method against Chain-of-Thought (COT) baselines (Table 2). It includes ablation studies (Table 3) and qualitative examples of generated layouts (Figure 12). Metrics such as space utilization, compliance, and constraint satisfaction are defined and reported. | L94: Partially | N94: Resolved | O94: see reasoning r1 | Q94: Resolved by reviewers
A95: D094 | B95: S3 – Hu et al. (2026) | C95: quality_appraisal | D95: quality_appraisal.q3_validity_and_limitation_discussion Type: AppraisalAnswer Q3: Are the boundaries of the contribution explicitly discussed (failure modes, scalability, external validity, domain assumptions)? Types: - Yes: Criterion fully met - Partially: Criterion partly met - No: Criterion not met | E95: categorical | F95: High | G95: Only R1: Partially | Only R2: Yes | H95: Partially | I95: Yes | J95: Sec. 5 notes the method 'is suitable when there is sufficient support from detailed equipment information and clear knowledge of equipment constraints, along with the need for expert involvement'. It also states that reasoning is 'more challenging when the constraints of the device are unknown' and that there is no downstream fine-tuning. The 2D simplification is acknowledged as an assumption (Sec. 3.2.1), and the inability to compare with traditional optimization methods is stated (Sec. 4.2). Missing from the discussion are threats to validity of the evaluation, such as the manual evaluation, the small dataset and the single case, as well as statistical robustness and scalability beyond 15 elements. | K95: Section 5 (Discussion) explicitly discusses limitations: the method relies on detailed equipment information and expert involvement; it struggles with unknown constraints or complex hard/soft constraint satisfaction without fine-tuning; and it notes that the current approach uses generalized LLM capabilities rather than downstream task adaptation. It also mentions the potential for Multi-Agent Systems as a future direction to handle complexity. | L95: Partially | N95: Resolved | O95: see reasoning r1 | Q95: Resolved by reviewers
A96: D095 | B96: S3 – Hu et al. (2026) | C96: quality_appraisal | D96: quality_appraisal.q4_positioning_against_prior_work Type: AppraisalAnswer Q4: Is the contribution compared against existing solutions with explicit differentiation? Types: - Yes: Criterion fully met - Partially: Criterion partly met - No: Criterion not met | E96: categorical | F96: High | G96: Only R1: Partially | Only R2: Yes | H96: Partially | I96: Yes | J96: Related work (Sec. 2) covers LLM spatial reasoning (3D-LLM, LayoutGPT, SpatialVLM), layout representations, and prompt engineering (CoT, ReAct, RAG). It identifies the gap: 'relatively little research on how to use large models to infer spatial and positional configurations through constraints'. Empirically, the paper compares only against CoT. It explicitly declines comparison with traditional optimization methods: 'generative methods are not directly comparable to traditional approaches.' Differentiation is therefore present but limited. | K96: Section 2 reviews related work in spatial reasoning of LLMs, layout structured representation, and prompt engineering. It explicitly contrasts the proposed method with traditional SLP, heuristic algorithms (GA, PSO), and reinforcement learning approaches (Klar et al.). It also differentiates from existing LLM layout works (LayoutGPT, 3D-LLM) by focusing on industrial shopfloor constraints and structured JSON representation. | L96: Partially | N96: Resolved | O96: see reasoning r1 | Q96: Resolved by reviewers
A97: D096 | B97: S3 – Hu et al. (2026) | C97: study | D97: consistency_flags Type: list[str] A6: soft cross-group consistency warnings for reviewers. Auto-computed, do not supply. | E97: free-text | F97: Medium | G97: Filled only by R2 | I97: llm_or_role should be 'none' iff optimization_tradition_present is false | L97: NA | N97: Resolved | P97: Triage | Q97: Moot – follows resolved field | R97: Resolved by setting D079 = none (Option A). Consistency flag holds: D075 = FALSE (no optimization) but D079 consensus llm_or_role = 'direct-optimizer; verifier'. Set D079 to 'none' or revisit D075.
A98: D097 | B98: S4 – Gao et al. (2026) | C98: bibliographic_metadata | D98: bibliographic_metadata.affiliations Type: list[str] Author affiliations as reported. | E98: free-text | F98: Medium | G98: Text differs (similarity 68%) | H98: School of Information Science and Technology, ShanghaiTech University, Shanghai, China; Advanced Institute of Information Technology (AIIT), Peking University, Hangzhou, China; School of Entrepreneurship and Management, ShanghaiTech University, Shanghai, China | I98: School of Information Science and Technology ShanghaiTech University; Advanced Institute of Information Technology (AIIT), Peking University; School of Entrepreneurship and Management ShanghaiTech University | L98: School of Information Science and Technology, ShanghaiTech University, Shanghai, China; Advanced Institute of Information Technology (AIIT), Peking University, Hangzhou, China; School of Entrepreneurship and Management, ShanghaiTech University, Shanghai, China | N98: Resolved | P98: Triage | Q98: No discussion needed | R98: R1 more complete (full names / grant numbers)
A99: D098 | B99: S4 – Gao et al. (2026) | C99: bibliographic_metadata | D99: bibliographic_metadata.funding_source Type: str Funding source as reported. NR if absent. | E99: free-text | F99: Medium | G99: Text differs (similarity 24%) | H99: National Natural Science Foundation of China (No. 62372298); National Key Research and Development Program of China (Grant 2022YFF0903302); Shanghai Engineering Research Center of Intelligent Vision and Imaging; Shanghai Frontiers Science Center of Human-centered Artificial Intelligence (ShangHAI); MoE Key Laboratory of Intelligent Perception and Human-Machine Collaboration (KLIP-HuMaCo) | I99: National Natural Science Foundation of China, National Key Research and Development Program of China, Shanghai Engineering Research Center of Intelligent Vision and Imaging, Shanghai Frontiers Science Center of Human-centered Artificial Intelligence (ShangHAI), MoE Key Laboratory of Intelligent Perception and HumanMachine Collaboration (KLIP-HuMaCo) | L99: National Natural Science Foundation of China (No. 62372298); National Key Research and Development Program of China (Grant 2022YFF0903302); Shanghai Engineering Research Center of Intelligent Vision and Imaging; Shanghai Frontiers Science Center of Human-centered Artificial Intelligence (ShangHAI); MoE Key Laboratory of Intelligent Perception and Human-Machine Collaboration (KLIP-HuMaCo) | N99: Resolved | P99: Triage | Q99: No discussion needed | R99: R1 more complete (full names / grant numbers)
A100: D099 | B100: S4 – Gao et al. (2026) | C100: bibliographic_metadata | D100: bibliographic_metadata.funding_description Type: str | None Free-text elaboration of funding context: grant numbers, funder role, or statement of no funding, as reported. | E100: free-text | F100: Medium | G100: Text differs (similarity 100%) | H100: This research was supported by the National Natural Science Foundation of China (No. 62372298), the National Key Research and Development Program of China under Grant 2022YFF0903302, the Shanghai Engineering Research Center of Intelligent Vision and Imaging, the Shanghai Frontiers Science Center of Human-centered Artificial Intelligence (ShangHAI), and the MoE Key Laboratory of Intelligent Perception and Human-Machine Collaboration (KLIP-HuMaCo). | I100: This research was supported by the National Natural Science Foundation of China (No. 62372298), the National Key Research and Development Program of China under Grant 2022YFF0903302, the Shanghai Engineering Research Center of Intelligent Vision and Imaging, the Shanghai Frontiers Science Center of Human-centered Artificial Intelligence (ShangHAI), and the MoE Key Laboratory of Intelligent Perception and HumanMachine Collaboration (KLIP-HuMaCo). | L100: This research was supported by the National Natural Science Foundation of China (No. 62372298), the National Key Research and Development Program of China under Grant 2022YFF0903302, the Shanghai Engineering Research Center of Intelligent Vision and Imaging, the Shanghai Frontiers Science Center of Human-centered Artificial Intelligence (ShangHAI), and the MoE Key Laboratory of Intelligent Perception and Human-Machine Collaboration (KLIP-HuMaCo). | N100: Resolved | P100: Triage | Q100: No discussion needed | R100: R1 more complete (full names / grant numbers)
...

Sheet Reasoning_Only
A1: Study | B1: Field group | C1: Reasoning field | D1: Linked value field(s) | E1: Value also disputed? | F1: Difference | G1: R1 reasoning | H1: R2 reasoning
A2: S1 – Schmitt et al. (2026) | B2: study_characterization | C2: study_characterization.research_type_rationale | D2: research_type | E2: Yes – see Comparison | F2: Text differs (similarity 4%) | G2: The paper proposes a novel end-to-end LLM-driven DES workflow (builder, inspector, visualizer, bottleneck, CPD, adaptor and evaluator agents) and evaluates it through 21 researcher-run experimental runs on two industrial production-line cases (Sec. 4.4, Sec. 5). Validation-research is chosen over evaluation-research because the workflow was not deployed in operational use by practitioners. The paper states: "Implementing the suggested changes in production fell outside the scope of this study" (Fig. 1 caption). Case B also used "a simplified mock-up event log", and the CPDs were fictitious (Sec. 4.2). Evaluation was through repeated experiments plus comparison against FACTS Analyzer models. Uncertainty (?): the cases come from a real company (Scania) and real MES data was used for Case A, so a reviewer could argue for evaluation-research under the 'industrial case studies' clause. | H2: The paper presents a novel LLM-driven workflow for discrete-event simulation (DES) and evaluates it using two real-world industrial case studies from a Swedish automotive manufacturer (Scania). The evaluation involves systematic analysis of 21 experimental runs, comparing generated models against commercial simulation software (FACTS Analyzer) with defined metrics (Throughput, WIP, SEC). This fits the definition of evaluation-research: 'Technique evaluated in practice (naturalistic setting: real organisation, real users, real data in operational use), incl. industrial case studies'. See Section 1 (Introduction), Section 4.2 (Use case and data collection), and Section 5 (Results).
A3: S1 – Schmitt et al. (2026) | B3: study_characterization | C3: study_characterization.validation_status_rationale | D3: validation_status | E3: No | F3: Text differs (similarity 5%) | G3: A working Python/SimPy implementation, released on GitHub, was evaluated under a defined protocol with defined metrics (Sec. 4.4, Sec. 5.3.4, Sec. 5.4.4, Sec. 5.5, Sec. 5.6). The protocol covered 10 runs for Case A and 11 runs for Case B, measuring code correctness, error types, CPD flagging, adaptation success and evaluation accuracy (Tables 5 and 7, Fig. 18). Input-output validation compared TH, WIP and SEC against FACTS Analyzer models using means, 95% confidence intervals and a 5%-10% acceptance threshold, following Sargent. Anchor: "21 experimental runs on two industrial case studies from a Swedish automotive manufacturer" (Abstract). | H3: The system is fully implemented (Python scripts, LLM API calls, blueprint model) and validated through a defined protocol. The authors conducted 21 experimental runs across two case studies, measured specific KPIs (TH, WIP, SEC), and performed input-output validation by comparing results against a commercial simulation tool (FACTS Analyzer) within acceptable thresholds (5-10%). This meets the criteria for 'implemented-validated': 'Working system + evaluation under a defined protocol with defined metrics'. See Section 4.4 (Workflow validation) and Section 5.6 (Validating the workflow with simulation software).
A4: S1 – Schmitt et al. (2026) | B4: study_characterization | C4: study_characterization.industry_sector_reasoning | D4: industry_sector | E4: Yes – see Comparison | F4: Text differs (similarity 25%) | G4: The cases come from "a large Swedish automotive manufacturer" (Sec. 1, Sec. 4.2). The affiliations name Scania CV AB. | H4: The paper explicitly states that the case studies are from 'a large Swedish automotive manufacturer' (identified as Scania CV AB in the author affiliations and abstract). The context is 'manufacturing industries' and 'production systems'. See Section 1 (Introduction) and Section 4.2 (Use case and data collection).
A5: S1 – Schmitt et al. (2026) | B5: study_characterization | C5: study_characterization.case_study_domain_reasoning | D5: case_study_domain | E5: Yes – see Comparison | F5: Text differs (similarity 3%) | G5: Sec. 4.4 and Sec. 5 describe "an automated assembly line and an automated machining line". Sec. 5.3 describes Case A as four sequential operations. Sec. 5.4 describes Case B as seven machines with two parallel presses. The KPIs were TH, WIP and SEC (Sec. 4.2). | H5: The core domain is the automation of Discrete-Event Simulation (DES) modeling for manufacturing systems. The specific application areas are capacity analysis, energy efficiency assessment, and bottleneck identification in production lines (machining and assembly). See Abstract and Section 2.2 (Manufacturing system simulation).
A6: S1 – Schmitt et al. (2026) | B6: study_characterization | C6: study_characterization.stated_research_questions_reasoning | D6: stated_research_questions | E6: No | F6: Text differs (similarity 45%) | G6: Both research questions are stated verbatim in Sec. 1 (Introduction). | H6: The research questions are explicitly listed in Section 1 (Introduction) under the paragraph starting with 'To achieve this, the paper addresses two research questions (RQs):'.
A7: S1 – Schmitt et al. (2026) | B7: strategic_planning_scope | C7: strategic_planning_scope.subdomain_mapping_rationale | D7: subdomain | E7: No | F7: Text differs (similarity 3%) | G7: The paper uses LLMs to generate, adapt and evaluate DES models of existing production lines: an automated machining line (Case A) and an automated assembly line (Case B) at a Swedish automotive manufacturer. The goal is capacity and energy-efficiency improvement of the lines (Sec. 1, 4, 5). Per Appendix A, simulation-based line and capacity planning within one site maps to factory-planning. This is a boundary case: it is a brownfield improvement of existing lines, and many adaptations are parametric (availability, MTTR, cycle time), which leans tactical or operational. Structural adaptations, however, also touch line configuration, such as adding a third parallel press or changing buffer capacities (Sec. 4.3.3, 5.4.3). No network, site or technology-selection scope. | H7: The paper focuses on the internal configuration and optimization of production lines (machining and assembly) within a single manufacturing site (Scania CV AB). It addresses capacity, energy efficiency, and inventory (WIP) for existing production lines. This aligns with 'factory-planning' as it deals with the internal logic, parameters, and structural variants of production systems rather than multi-site network design or site selection. The scope is limited to the internal configuration of the factory lines.
A8: S1 – Schmitt et al. (2026) | B8: strategic_planning_scope | C8: strategic_planning_scope.planning_task_type_reasoning | D8: planning_task_type | E8: No | F8: Text differs (similarity 6%) | G8: The core task is automated DES model generation, adaptation and evaluation (title; Sec. 4.3). Capacity-dimensioning is included because the bottleneck-agent and adaptor-agent propose and implement changes to buffer capacities and add a third parallel press. This is evaluated on throughput, WIP and SEC (Sec. 5.3.3, 5.4.3, Fig. 14). Material-flow-design was considered but not selected: part-flow logic is extracted, not designed. That choice is uncertain (?). | H8: The primary task is 'simulation-modeling' as the core contribution is an LLM-driven framework for generating, adapting, and evaluating Discrete-Event Simulation (DES) models (Abstract, Section 1). The application of this modeling is for 'capacity-dimensioning' and analysis, specifically assessing throughput, bottlenecks, and energy efficiency to support decision-making on process improvements and resource allocation (Section 1, Section 4.2). It does not involve layout planning or network configuration.
A9: S1 – Schmitt et al. (2026) | B9: strategic_planning_scope | C9: strategic_planning_scope.scp_process_reasoning | D9: scp_process | E9: No | F9: Text differs (similarity 3%) | G9: All decisions concern production lines: machines, buffers, throughput and energy per part (Sec. 4.2, 5). No procurement, distribution or sales aspects are addressed. | H9: The study explicitly deals with manufacturing production lines, machine performance, part flow, and production schedules. It does not address procurement, distribution, or sales processes. Section 1 states: 'manufacturing engineering has adapted and developed tools to design and manage production systems'.
A10: S1 – Schmitt et al. (2026) | B10: strategic_planning_scope | C10: strategic_planning_scope.vdi5200_phase_reasoning | D10: vdi5200_phase | E10: Yes – see Comparison | F10: Text differs (similarity 3%) | G10: VDI 5200 is not referenced. The method evaluates line variants via simulation: structural changes such as adding a parallel station, and buffer dimensioning (Sec. 4.3.3). This fits concept-planning dimensioning and variant evaluation as well as detailed-planning parameter refinement. The mapping is uncertain (?) because the study concerns improvement of existing lines rather than a new factory planning project. Implementation in production is explicitly out of scope (Fig. 1 caption). | H10: The method supports evaluating different configurations (e.g., buffer sizes, parallel stations) to determine the best improvement. This is a conceptual evaluation of system variants, aligning with VDI 5200 Phase 3 (Konzeptplanung). It is not Phase 4 (Detailplanung) as it doesn't produce detailed engineering drawings or specific component specs, nor Phase 1/2 as the objectives and basis are already defined by the case studies.
A11: S1 – Schmitt et al. (2026) | B11: strategic_planning_scope | C11: strategic_planning_scope.time_horizon_explicitly_stated_reasoning | D11: time_horizon_explicitly_stated | E11: No | F11: Text differs (similarity 17%) | G11: Only simulation horizons are stated: 30 days for Case A and 7 days for Case B, each with a 1-day warm-up (Sec. 4.3.2, Fig. 5, Fig. 11). These are model run lengths, not planning horizons. No planning horizon is given. | H11: The paper discusses simulation horizons (e.g., 30 days, 7 days) for the DES models to reach steady state, but does not state a strategic planning time horizon (e.g., '5-year plan'). The focus is on operational/short-term performance analysis and immediate process improvements, not long-term strategic horizons.
A12: S1 – Schmitt et al. (2026) | B12: strategic_planning_scope | C12: strategic_planning_scope.planning_horizon_rationale | D12: planning_horizon_tiers | E12: Yes – see Comparison | F12: Text differs (similarity 2%) | G12: No horizon statements appear in the paper; the tiers are reviewer judgement. Strategic: structural changes determine what exists, e.g. 'Add a third parallel press with its own pre-buffer instance' (Fig. 14) and buffer capacity increases (Fig. 7, 14). Tactical: parametric improvements of existing machines, such as availability, cycle time, MTTR and defect rate (Table 5, Table 7). The strategic tier is borderline (?) because the decisions concern line-level modification within an existing plant. | H12: The method supports decisions that configure the system structure, such as adding or removing operations (structural adaptations) and changing buffer capacities. According to the schema definition, 'Strategic' is selected iff system_configuring_decision is true. These decisions determine what exists in the system (e.g., number of parallel presses), which is a system configuration decision.
... A124: S3 – Hu et al. (2026) | B124: strategic_planning_scope | C124: strategic_planning_scope.theoretical_framework_cited_reasoning | D124: theoretical_framework_cited | E124: Yes – see Comparison | F124: Text differs (similarity 4%) | G124: Muther's Systematic Layout Planning (SLP) is mentioned only as background in the Introduction ('the most classic approach is Richard Muther's Systematic Layout Planning'). It is not used to structure the method. CoT, ReAct and RAG are prompting techniques and do not count. | H124: The paper cites 'Systematic Layout Planning (SLP)' by Richard Muther as the 'most classic approach' in Section 1. While SLP is a methodology/framework for layout planning, it is not one of the specific strategic planning frameworks listed in the enum (VDI-5200, SC-Planning-Matrix, etc.). Therefore, 'other' is the appropriate category, specifying SLP.
A125: S3 – Hu et al. (2026) | B125: strategic_planning_scope | C125: strategic_planning_scope.theoretical_framework_rationale | D125: theoretical_framework_cited | E125: Yes – see Comparison | F125: Filled only by R1 | G125: The method is structured around prompt engineering (task decomposition into Role/Space/Factory/Request, equipment models, and a think-generate-evaluate iteration) rather than any planning-domain framework. SLP and VDI 5200 are not used to structure the scope.
